Workbook
Name NativeTimeline_Date___Time: #N/A
Name Slicer_Payment_Method: #N/A
Name Slicer_PSP_Provider: #N/A

Sheet Documentation
A1: 📄 PSP Performance Architecture — Documentation
A2: Payment Service Provider Transaction Analysis · FY2024 · Nikolas Andreou
A4: PROJECT OVERVIEW
A5: Objective | B5: Analyze PSP transaction performance across 5 payment providers, 10 European markets, and 5 payment methods to identify optimization opportunities for conversion rates, revenue, and cost efficiency.
A6: Dataset | B6: 1,000 synthetic transactions spanning January–December 2024, covering SEK, NOK, EUR, GBP, and PLN currencies. All monetary values normalized to EUR for cross-market comparability.
A7: Scope | B7: Conversion rate analysis, revenue & fee benchmarking, geographic performance, decline reason diagnosis, and best-provider-per-market recommendations.
A8: Tools Used | B8: Microsoft Excel — formulas (COUNTIFS, SUMIFS, AVERAGEIFS, VLOOKUP, XLOOKUP, INDEX/MATCH, UNIQUE, SORT, FILTER), pivot tables, conditional formatting, dashboard design. Power Query — used to merge Raw Data (Jan-Jun) and Raw Data (Jul-Dec) into Raw_Data_Combined with FX rate lookups for multi-currency normalization.
A9: DATA DESCRIPTION
A10: Field | B10: Description | C10: Example
A11: Transaction ID | B11: Unique identifier for each transaction | C11: TXN00108
A12: Date & Time | B12: Transaction timestamp (Excel serial date) | C12: 45292.913
A13: GEO | B13: ISO 2-letter country code | C13: SE, NO, ES, FR, GB, PL, NL, IT, CY, DE
A14: Currency | B14: Original transaction currency | C14: SEK, NOK, EUR, GBP, PLN
A15: PSP Provider | B15: Payment service provider processing the transaction | C15: Worldpay, Stripe, Checkout.com, PaySafe, Adyen
A16: Payment Method | B16: Customer payment instrument | C16: Credit Card, Debit Card, E-Wallet, Bank Transfer, Crypto
A17: Amount | B17: Transaction amount in original currency | C17: 4,887.84 NOK
A18: Status | B18: Transaction outcome | C18: Success, Pending, Failed
A19: Decline Reason | B19: Reason for failure (Failed transactions only) | C19: Card Declined, Technical Error, Fraud Suspected, Insufficient Funds, Expired Card
A20: Fee % | B20: Provider fee rate applied to successful transactions | C20: 1.9%, 2.1%, 2.5%, 2.9%, 3.2%
A21: Exchange Rate to EUR | B21: Conversion rate from original currency to EUR | C21: SEK: 0.0874
A22: Fee Amount EUR | B22: Fee in EUR (Amount × Rate × Fee% for Success only) | C22: 10.51
A23: Net Amount EUR | B23: Revenue after fees in EUR (Gross − Fee) | C23: 420.35
A24: Gross Amount EUR | B24: Total in EUR before fees (Amount × Exchange Rate) | C24: 409.85
A25: Month Name | B25: Calendar month derived from Date & Time | C25: January
A26: KEY ASSUMPTIONS & METHODOLOGY
A27: Currency Conversion | B27: All non-EUR amounts converted using fixed mid-market rates sourced from European Central Bank (ECB). Rates represent annual averages for 2024. See "FX Rates" tab for full rate table.
A28: Fee Calculation | B28: Fees are modeled as percentage-based rates only (e.g., 1.9%, 2.1%, 2.5%). In practice, PSP providers often charge a combination of percentage fees and fixed per-transaction fees (e.g., €0.20/txn). Fixed fees are acknowledged but not included in this analysis, as the synthetic dataset only provides rate-based fees. All fee calculations apply exclusively to successful transactions — Pending and Failed transactions carry €0 fees.
A29: Success Rate | B29: Defined as: COUNT(Status="Success") / COUNT(All Transactions). Pending transactions are NOT counted as failures.
A30: Net Amount EUR | B30: Gross Amount EUR − Fee Amount EUR. Only non-zero for successful transactions.
A31: Avg Transaction (All) | B31: AVERAGE across all 1,000 rows including €0 values for Pending/Failed. Denominator = total transactions.
A32: Avg Successful Txn | B32: AVERAGEIFS filtered to Status="Success" only. Denominator = successful transactions (554).
A33: GEO Ranking | B33: GEOs ranked by total transaction count. "Top 3" analysis covers NL (125), GB (113), CY (108).
A34: Decline Analysis | B34: Percentages calculated as share of failed transactions only (218 total), not share of all 1,000 transactions.
A35: SHEET INDEX
A36: # | B36: Sheet Name | C36: Purpose
A37: 1 | B37: Documentation | C37: This sheet — project overview, methodology, and assumptions
A38: 2 | B38: Raw Data (Jan-Jun) | C38: Original transaction records for January–June 2024 (485 rows)
A39: 3 | B39: Raw Data (Jul-Dec) | C39: Original transaction records for July–December 2024 (515 rows)
A40: 4 | B40: FX Rates | C40: Exchange rate reference table (SEK, NOK, EUR, GBP, PLN → EUR) with sources
A41: 5 | B41: Raw_Data_Combined | C41: Merged dataset with EUR-normalized columns (1,000 rows × 15 fields)
A42: 6 | B42: Tasks | C42: Analytical tasks: conversion rates, revenue/fees, GEO performance, declines, best PSP per GEO, pending transaction analysis
A43: 7 | B43: Dashboards | C43: Static summary dashboard with KPIs, provider table, monthly trends, GEO breakdown
A44: 8 | B44: Pivot Tables | C44: Pivot table outputs for revenue trends, status, geography, fees, declines, payment methods
A45: 9 | B45: Dynamic Dashboard | C45: Visual dashboard with charts — revenue trends, status breakdown, geography, fees, declines, payment methods
A46: KEY FINDINGS
A47: 1. Conversion Rates | B47: Overall success rate: 55.4% (554/1,000). Checkout.com leads at 58.8%, while Adyen trails at 51.9%. Significant room for improvement across all providers — industry benchmarks typically target 70–85%.
A48: 2. Revenue Distribution | B48: Total net revenue: ~€1,024K after ~€26.3K in fees. Checkout.com generates the highest net revenue (€249.3K) with the lowest fee rate (1.9%). PaySafe has the highest fee rate (3.2%) but still ranks #2 by volume.
A49: 3. Geographic Performance | B49: France leads in success rate (63.4%) while SE and DE lag (~49%). Revenue concentration is uneven — FR, GB, NL, and CY each contribute >€149K, while SE and NO contribute <€12K due to lower EUR-equivalent values.
A50: 4. Decline Reasons | B50: Fraud Suspected (23.4%) and Card Declined (22.5%) are the top failure causes. Together they account for nearly half of all declines, suggesting potential gains from improved fraud screening and retry logic.
A51: 5. Pending Transactions | B51: 228 transactions (22.8%) remain in Pending status — a significant operational concern. Worldpay (24.7%) and Stripe (24.2%) have the highest pending rates by provider; GB (24.8%) leads by GEO. Pending analysis added in Task 6.
A52: 6. Best PSP per Market | B52: Optimal provider varies by GEO: Adyen is strongest in NL (63.2%), Checkout.com in GB (65.4%), and PaySafe in CY (70.0%). A multi-PSP routing strategy could lift overall conversion.
A53: Prepared by Nikolas Andreou · 2024 · For portfolio / recruitment purposes · Data is synthetic

Sheet Raw Data (Jan-Jun)
A1: Transaction ID | B1: Date & Time | C1: GEO | D1: Currency | E1: PSP Provider | F1: Payment Method | G1: Amount | H1: Status | I1: Decline Reason | J1: Fee % | K1: Fee Amount | L1: Net Amount
A2: TXN00108 | B2: 45292.913 | C2: SE | D2: SEK | E2: Worldpay | F2: Bank Transfer | G2: 280.48 | H2: Pending | J2: 2.5 | K2: 0 | L2: 0
A3: TXN00929 | B3: 45294.356 | C3: NO | D3: NOK | E3: Worldpay | F3: E-Wallet | G3: 4887.84 | H3: Success | J3: 2.5 | K3: 122.2 | L3: 4765.64
A4: TXN00542 | B4: 45294.427 | C4: ES | D4: EUR | E4: Worldpay | F4: E-Wallet | G4: 4202.15 | H4: Success | J4: 2.5 | K4: 105.05 | L4: 4097.1
A5: TXN00520 | B5: 45294.437 | C5: FR | D5: EUR | E5: Stripe | F5: Debit Card | G5: 4643.85 | H5: Pending | J5: 2.9 | K5: 0 | L5: 0
A6: TXN00794 | B6: 45295.008 | C6: GB | D6: GBP | E6: Checkout.com | F6: E-Wallet | G6: 2086.95 | H6: Failed | I6: Card Declined | J6: 1.9 | K6: 0 | L6: 0
A7: TXN00712 | B7: 45295.155 | C7: PL | D7: PLN | E7: PaySafe | F7: Bank Transfer | G7: 3624.74 | H7: Pending | J7: 3.2 | K7: 0 | L7: 0
A8: TXN00652 | B8: 45295.385 | C8: ES | D8: EUR | E8: PaySafe | F8: Credit Card | G8: 3859.9 | H8: Success | J8: 3.2 | K8: 123.52 | L8: 3736.38
A9: TXN00600 | B9: 45296.226 | C9: NL | D9: EUR | E9: Adyen | F9: Crypto | G9: 2674.57 | H9: Success | J9: 2.1 | K9: 56.17 | L9: 2618.4
A10: TXN00388 | B10: 45296.467 | C10: IT | D10: EUR | E10: Checkout.com | F10: E-Wallet | G10: 3700.48 | H10: Success | J10: 1.9 | K10: 70.31 | L10: 3630.17
A11: TXN00617 | B11: 45296.577 | C11: IT | D11: EUR | E11: Checkout.com | F11: Debit Card | G11: 3985.87 | H11: Pending | J11: 1.9 | K11: 0 | L11: 0
A12: TXN00494 | B12: 45297.874 | C12: FR | D12: EUR | E12: Checkout.com | F12: Bank Transfer | G12: 4260.84 | H12: Success | J12: 1.9 | K12: 80.96 | L12: 4179.88
A13: TXN00643 | B13: 45298.278 | C13: NL | D13: EUR | E13: Stripe | F13: Bank Transfer | G13: 4007.09 | H13: Success | J13: 2.9 | K13: 116.21 | L13: 3890.88
A14: TXN00630 | B14: 45299.243 | C14: IT | D14: EUR | E14: Checkout.com | F14: Credit Card | G14: 1985.08 | H14: Success | J14: 1.9 | K14: 37.72 | L14: 1947.36
A15: TXN00292 | B15: 45299.291 | C15: ES | D15: EUR | E15: Stripe | F15: Bank Transfer | G15: 4573.06 | H15: Pending | J15: 2.9 | K15: 0 | L15: 0
A16: TXN00726 | B16: 45299.816 | C16: SE | D16: SEK | E16: Stripe | F16: Debit Card | G16: 2717.22 | H16: Pending | J16: 2.9 | K16: 0 | L16: 0
A17: TXN00265 | B17: 45299.973 | C17: IT | D17: EUR | E17: Checkout.com | F17: Debit Card | G17: 885.72 | H17: Failed | I17: Technical Error | J17: 1.9 | K17: 0 | L17: 0
A18: TXN00282 | B18: 45300.301 | C18: GB | D18: GBP | E18: Stripe | F18: Crypto | G18: 177.55 | H18: Pending | J18: 2.9 | K18: 0 | L18: 0
A19: TXN00860 | B19: 45301.658 | C19: CY | D19: EUR | E19: Stripe | F19: Debit Card | G19: 548.01 | H19: Pending | J19: 2.9 | K19: 0 | L19: 0
A20: TXN00545 | B20: 45301.694 | C20: DE | D20: EUR | E20: Checkout.com | F20: Crypto | G20: 2031.62 | H20: Pending | J20: 1.9 | K20: 0 | L20: 0
A21: TXN00896 | B21: 45301.865 | C21: SE | D21: SEK | E21: Adyen | F21: Crypto | G21: 2501.03 | H21: Failed | I21: Fraud Suspected | J21: 2.1 | K21: 0 | L21: 0
A22: TXN00920 | B22: 45302.041 | C22: SE | D22: SEK | E22: Checkout.com | F22: Debit Card | G22: 4535.16 | H22: Failed | I22: Card Declined | J22: 1.9 | K22: 0 | L22: 0
A23: TXN00426 | B23: 45302.428 | C23: GB | D23: GBP | E23: Stripe | F23: E-Wallet | G23: 858.82 | H23: Failed | I23: Card Declined | J23: 2.9 | K23: 0 | L23: 0
A24: TXN00634 | B24: 45302.933 | C24: PL | D24: PLN | E24: Adyen | F24: E-Wallet | G24: 4494.33 | H24: Failed | I24: Technical Error | J24: 2.1 | K24: 0 | L24: 0
A25: TXN00280 | B25: 45303.395 | C25: SE | D25: SEK | E25: Worldpay | F25: Crypto | G25: 1902.59 | H25: Success | J25: 2.5 | K25: 47.56 | L25: 1855.03
A26: TXN00724 | B26: 45303.783 | C26: IT | D26: EUR | E26: Adyen | F26: E-Wallet | G26: 1010.77 | H26: Success | J26: 2.1 | K26: 21.23 | L26: 989.54
A27: TXN00047 | B27: 45304.241 | C27: PL | D27: PLN | E27: Worldpay | F27: Debit Card | G27: 1341.36 | H27: Success | J27: 2.5 | K27: 33.53 | L27: 1307.83
A28: TXN00526 | B28: 45304.703 | C28: PL | D28: PLN | E28: Checkout.com | F28: Crypto | G28: 2233.33 | H28: Success | J28: 1.9 | K28: 42.43 | L28: 2190.9
A29: TXN00049 | B29: 45304.883 | C29: CY | D29: EUR | E29: PaySafe | F29: E-Wallet | G29: 4323.12 | H29: Success | J29: 3.2 | K29: 138.34 | L29: 4184.78
A30: TXN00848 | B30: 45306.158 | C30: IT | D30: EUR | E30: Worldpay | F30: Credit Card | G30: 2998.47 | H30: Success | J30: 2.5 | K30: 74.96 | L30: 2923.51
A31: TXN00404 | B31: 45307.53 | C31: CY | D31: EUR | E31: Adyen | F31: E-Wallet | G31: 1081.43 | H31: Success | J31: 2.1 | K31: 22.71 | L31: 1058.72
A32: TXN00980 | B32: 45307.59 | C32: DE | D32: EUR | E32: Checkout.com | F32: Credit Card | G32: 433.04 | H32: Success | J32: 1.9 | K32: 8.23 | L32: 424.81
A33: TXN00641 | B33: 45308.254 | C33: NL | D33: EUR | E33: Adyen | F33: Credit Card | G33: 168.77 | H33: Failed | I33: Technical Error | J33: 2.1 | K33: 0 | L33: 0
A34: TXN00011 | B34: 45308.434 | C34: IT | D34: EUR | E34: Stripe | F34: Debit Card | G34: 4566.55 | H34: Pending | J34: 2.9 | K34: 0 | L34: 0
A35: TXN00879 | B35: 45308.581 | C35: GB | D35: GBP | E35: Worldpay | F35: Bank Transfer | G35: 1579.65 | H35: Failed | I35: Technical Error | J35: 2.5 | K35: 0 | L35: 0
A36: TXN00996 | B36: 45308.965 | C36: SE | D36: SEK | E36: PaySafe | F36: Credit Card | G36: 3011.99 | H36: Failed | I36: Insufficient Funds | J36: 3.2 | K36: 0 | L36: 0
A37: TXN00215 | B37: 45309.169 | C37: ES | D37: EUR | E37: PaySafe | F37: E-Wallet | G37: 1920.44 | H37: Pending | J37: 3.2 | K37: 0 | L37: 0
A38: TXN00627 | B38: 45309.27 | C38: GB | D38: GBP | E38: Checkout.com | F38: Debit Card | G38: 2369.4 | H38: Success | J38: 1.9 | K38: 45.02 | L38: 2324.38
A39: TXN00612 | B39: 45309.89 | C39: PL | D39: PLN | E39: Worldpay | F39: Bank Transfer | G39: 4875.16 | H39: Pending | J39: 2.5 | K39: 0 | L39: 0
A40: TXN00118 | B40: 45310.189 | C40: NO | D40: NOK | E40: PaySafe | F40: Credit Card | G40: 4372.21 | H40: Failed | I40: Insufficient Funds | J40: 3.2 | K40: 0 | L40: 0
A41: TXN00207 | B41: 45310.383 | C41: DE | D41: EUR | E41: Adyen | F41: Credit Card | G41: 1584.82 | H41: Success | J41: 2.1 | K41: 33.28 | L41: 1551.54
A42: TXN00330 | B42: 45310.489 | C42: SE | D42: SEK | E42: Checkout.com | F42: Credit Card | G42: 555.75 | H42: Success | J42: 1.9 | K42: 10.56 | L42: 545.19
A43: TXN00963 | B43: 45310.642 | C43: NL | D43: EUR | E43: Checkout.com | F43: Crypto | G43: 3625.82 | H43: Failed | I43: Card Declined | J43: 1.9 | K43: 0 | L43: 0
A44: TXN00546 | B44: 45310.719 | C44: SE | D44: SEK | E44: Checkout.com | F44: Bank Transfer | G44: 3273 | H44: Success | J44: 1.9 | K44: 62.19 | L44: 3210.81
A45: TXN00385 | B45: 45310.744 | C45: CY | D45: EUR | E45: Adyen | F45: E-Wallet | G45: 1248.83 | H45: Success | J45: 2.1 | K45: 26.23 | L45: 1222.6
A46: TXN00048 | B46: 45311.635 | C46: ES | D46: EUR | E46: Worldpay | F46: E-Wallet | G46: 1532.9 | H46: Success | J46: 2.5 | K46: 38.32 | L46: 1494.58
A47: TXN00181 | B47: 45312.323 | C47: NL | D47: EUR | E47: Worldpay | F47: Crypto | G47: 2618.51 | H47: Success | J47: 2.5 | K47: 65.46 | L47: 2553.05
A48: TXN00550 | B48: 45312.325 | C48: NL | D48: EUR | E48: Adyen | F48: Credit Card | G48: 1329.14 | H48: Success | J48: 2.1 | K48: 27.91 | L48: 1301.23
A49: TXN00525 | B49: 45312.914 | C49: PL | D49: PLN | E49: Worldpay | F49: Credit Card | G49: 1935.52 | H49: Pending | J49: 2.5 | K49: 0 | L49: 0
A50: TXN00256 | B50: 45313.406 | C50: GB | D50: GBP | E50: PaySafe | F50: Bank Transfer | G50: 3283.3 | H50: Failed | I50: Card Declined | J50: 3.2 | K50: 0 | L50: 0
A51: TXN00403 | B51: 45313.585 | C51: FR | D51: EUR | E51: Checkout.com | F51: Bank Transfer | G51: 4110.21 | H51: Failed | I51: Technical Error | J51: 1.9 | K51: 0 | L51: 0
A52: TXN00631 | B52: 45313.785 | C52: NL | D52: EUR | E52: Checkout.com | F52: Debit Card | G52: 1863.28 | H52: Success | J52: 1.9 | K52: 35.4 | L52: 1827.88
A53: TXN00384 | B53: 45314.01 | C53: DE | D53: EUR | E53: Worldpay | F53: E-Wallet | G53: 1921.07 | H53: Success | J53: 2.5 | K53: 48.03 | L53: 1873.04
A54: TXN00811 | B54: 45314.062 | C54: SE | D54: SEK | E54: Stripe | F54: Bank Transfer | G54: 2660.3 | H54: Failed | I54: Insufficient Funds | J54: 2.9 | K54: 0 | L54: 0
A55: TXN00491 | B55: 45315.094 | C55: PL | D55: PLN | E55: Stripe | F55: Crypto | G55: 3839.97 | H55: Pending | J55: 2.9 | K55: 0 | L55: 0
A56: TXN00973 | B56: 45315.72 | C56: FR | D56: EUR | E56: Checkout.com | F56: Crypto | G56: 3350.73 | H56: Success | J56: 1.9 | K56: 63.66 | L56: 3287.07
A57: TXN00230 | B57: 45315.867 | C57: NO | D57: NOK | E57: PaySafe | F57: Debit Card | G57: 3837.13 | H57: Failed | I57: Expired Card | J57: 3.2 | K57: 0 | L57: 0
A58: TXN00999 | B58: 45316.414 | C58: IT | D58: EUR | E58: Adyen | F58: Debit Card | G58: 4097.43 | H58: Failed | I58: Insufficient Funds | J58: 2.1 | K58: 0 | L58: 0
A59: TXN00072 | B59: 45317.35 | C59: PL | D59: PLN | E59: Adyen | F59: Bank Transfer | G59: 1640.96 | H59: Failed | I59: Fraud Suspected | J59: 2.1 | K59: 0 | L59: 0
A60: TXN00062 | B60: 45317.719 | C60: GB | D60: GBP | E60: Worldpay | F60: Debit Card | G60: 4009.07 | H60: Pending | J60: 2.5 | K60: 0 | L60: 0
A61: TXN00445 | B61: 45317.979 | C61: IT | D61: EUR | E61: PaySafe | F61: Credit Card | G61: 1695.95 | H61: Success | J61: 3.2 | K61: 54.27 | L61: 1641.68
A62: TXN00962 | B62: 45318.417 | C62: GB | D62: GBP | E62: Worldpay | F62: Bank Transfer | G62: 4244.6 | H62: Pending | J62: 2.5 | K62: 0 | L62: 0
A63: TXN00928 | B63: 45318.458 | C63: ES | D63: EUR | E63: Worldpay | F63: E-Wallet | G63: 4983.73 | H63: Pending | J63: 2.5 | K63: 0 | L63: 0
A64: TXN00248 | B64: 45318.771 | C64: FR | D64: EUR | E64: Checkout.com | F64: Crypto | G64: 3875.28 | H64: Failed | I64: Card Declined | J64: 1.9 | K64: 0 | L64: 0
A65: TXN00934 | B65: 45319.256 | C65: DE | D65: EUR | E65: Adyen | F65: Debit Card | G65: 188.95 | H65: Success | J65: 2.1 | K65: 3.97 | L65: 184.98
A66: TXN00346 | B66: 45319.458 | C66: NL | D66: EUR | E66: Adyen | F66: Debit Card | G66: 4077.93 | H66: Pending | J66: 2.1 | K66: 0 | L66: 0
A67: TXN00167 | B67: 45320.009 | C67: IT | D67: EUR | E67: Adyen | F67: Debit Card | G67: 3823.16 | H67: Success | J67: 2.1 | K67: 80.29 | L67: 3742.87
A68: TXN00903 | B68: 45320.097 | C68: NO | D68: NOK | E68: PaySafe | F68: Credit Card | G68: 4503.87 | H68: Failed | I68: Fraud Suspected | J68: 3.2 | K68: 0 | L68: 0
A69: TXN00414 | B69: 45320.318 | C69: ES | D69: EUR | E69: Stripe | F69: Crypto | G69: 2395.17 | H69: Success | J69: 2.9 | K69: 69.46 | L69: 2325.71
A70: TXN00886 | B70: 45320.885 | C70: ES | D70: EUR | E70: Adyen | F70: E-Wallet | G70: 2966.73 | H70: Success | J70: 2.1 | K70: 62.3 | L70: 2904.43
A71: TXN00942 | B71: 45320.961 | C71: SE | D71: SEK | E71: Checkout.com | F71: Bank Transfer | G71: 471.83 | H71: Success | J71: 1.9 | K71: 8.96 | L71: 462.87
A72: TXN00033 | B72: 45321.067 | C72: NL | D72: EUR | E72: Checkout.com | F72: Crypto | G72: 795.59 | H72: Pending | J72: 1.9 | K72: 0 | L72: 0
A73: TXN00020 | B73: 45321.331 | C73: NO | D73: NOK | E73: Stripe | F73: Credit Card | G73: 3662.22 | H73: Success | J73: 2.9 | K73: 106.2 | L73: 3556.02
A74: TXN00275 | B74: 45321.728 | C74: IT | D74: EUR | E74: Stripe | F74: Bank Transfer | G74: 1279.74 | H74: Success | J74: 2.9 | K74: 37.11 | L74: 1242.63
A75: TXN00884 | B75: 45323.026 | C75: DE | D75: EUR | E75: Adyen | F75: E-Wallet | G75: 1750.9 | H75: Pending | J75: 2.1 | K75: 0 | L75: 0
A76: TXN00744 | B76: 45323.498 | C76: SE | D76: SEK | E76: Stripe | F76: Credit Card | G76: 3519.74 | H76: Success | J76: 2.9 | K76: 102.07 | L76: 3417.67
A77: TXN00964 | B77: 45323.667 | C77: CY | D77: EUR | E77: Checkout.com | F77: E-Wallet | G77: 2770.75 | H77: Success | J77: 1.9 | K77: 52.64 | L77: 2718.11
A78: TXN00757 | B78: 45323.854 | C78: NO | D78: NOK | E78: Adyen | F78: Crypto | G78: 267.58 | H78: Success | J78: 2.1 | K78: 5.62 | L78: 261.96
A79: TXN00201 | B79: 45324.162 | C79: NL | D79: EUR | E79: Checkout.com | F79: Crypto | G79: 92.01 | H79: Pending | J79: 1.9 | K79: 0 | L79: 0
A80: TXN00790 | B80: 45324.269 | C80: PL | D80: PLN | E80: Worldpay | F80: E-Wallet | G80: 612.8 | H80: Pending | J80: 2.5 | K80: 0 | L80: 0
... A84: TXN00336 | B84: 45326.376 | C84: GB | D84: GBP | E84: Stripe | F84: E-Wallet | G84: 3243.37 | H84: Success | J84: 2.9 | K84: 94.06 | L84: 3149.31
A85: TXN00671 | B85: 45326.529 | C85: IT | D85: EUR | E85: PaySafe | F85: Credit Card | G85: 105.2 | H85: Failed | I85: Card Declined | J85: 3.2 | K85: 0 | L85: 0
A86: TXN00162 | B86: 45327.199 | C86: DE | D86: EUR | E86: Stripe | F86: Crypto | G86: 1083.51 | H86: Failed | I86: Technical Error | J86: 2.9 | K86: 0 | L86: 0
A87: TXN00114 | B87: 45327.367 | C87: CY | D87: EUR | E87: PaySafe | F87: Crypto | G87: 1343.19 | H87: Success | J87: 3.2 | K87: 42.98 | L87: 1300.21
A88: TXN00787 | B88: 45328.074 | C88: FR | D88: EUR | E88: Worldpay | F88: Credit Card | G88: 2361.39 | H88: Pending | J88: 2.5 | K88: 0 | L88: 0
A89: TXN00606 | B89: 45328.09 | C89: PL | D89: PLN | E89: Adyen | F89: E-Wallet | G89: 1591.22 | H89: Success | J89: 2.1 | K89: 33.42 | L89: 1557.8
A90: TXN00645 | B90: 45328.378 | C90: ES | D90: EUR | E90: Checkout.com | F90: Credit Card | G90: 515.11 | H90: Success | J90: 1.9 | K90: 9.79 | L90: 505.32
A91: TXN00169 | B91: 45328.538 | C91: DE | D91: EUR | E91: Worldpay | F91: Credit Card | G91: 2304.17 | H91: Success | J91: 2.5 | K91: 57.6 | L91: 2246.57
A92: TXN00025 | B92: 45328.677 | C92: IT | D92: EUR | E92: Worldpay | F92: Debit Card | G92: 2700.78 | H92: Pending | J92: 2.5 | K92: 0 | L92: 0
A93: TXN00373 | B93: 45328.706 | C93: DE | D93: EUR | E93: PaySafe | F93: E-Wallet | G93: 668.59 | H93: Pending | J93: 3.2 | K93: 0 | L93: 0
A94: TXN00315 | B94: 45329.095 | C94: FR | D94: EUR | E94: Worldpay | F94: Debit Card | G94: 3700.88 | H94: Success | J94: 2.5 | K94: 92.52 | L94: 3608.36
A95: TXN00224 | B95: 45329.181 | C95: GB | D95: GBP | E95: Worldpay | F95: Bank Transfer | G95: 3403.74 | H95: Success | J95: 2.5 | K95: 85.09 | L95: 3318.65
A96: TXN00291 | B96: 45329.285 | C96: NO | D96: NOK | E96: Checkout.com | F96: Debit Card | G96: 2402.18 | H96: Success | J96: 1.9 | K96: 45.64 | L96: 2356.54
A97: TXN00241 | B97: 45329.522 | C97: NL | D97: EUR | E97: Checkout.com | F97: E-Wallet | G97: 4128.3 | H97: Pending | J97: 1.9 | K97: 0 | L97: 0
A98: TXN00427 | B98: 45330.748 | C98: GB | D98: GBP | E98: PaySafe | F98: Crypto | G98: 4926.53 | H98: Failed | I98: Insufficient Funds | J98: 3.2 | K98: 0 | L98: 0
A99: TXN00357 | B99: 45330.868 | C99: GB | D99: GBP | E99: Worldpay | F99: Crypto | G99: 3751.51 | H99: Success | J99: 2.5 | K99: 93.79 | L99: 3657.72
A100: TXN00300 | B100: 45330.877 | C100: DE | D100: EUR | E100: Worldpay | F100: Debit Card | G100: 4214.3 | H100: Success | J100: 2.5 | K100: 105.36 | L100: 4108.94
A101: TXN00188 | B101: 45331.412 | C101: GB | D101: GBP | E101: Checkout.com | F101: Crypto | G101: 4177.25 | H101: Pending | J101: 1.9 | K101: 0 | L101: 0
A102: TXN00386 | B102: 45331.766 | C102: GB | D102: GBP | E102: Checkout.com | F102: Credit Card | G102: 904.93 | H102: Pending | J102: 1.9 | K102: 0 | L102: 0
A103: TXN00894 | B103: 45331.869 | C103: IT | D103: EUR | E103: Checkout.com | F103: E-Wallet | G103: 2170.22 | H103: Pending | J103: 1.9 | K103: 0 | L103: 0
...

Sheet Raw Data (Jul-Dec)
A1: Transaction ID | B1: Date & Time | C1: GEO | D1: Currency | E1: PSP Provider | F1: Payment Method | G1: Amount | H1: Status | I1: Decline Reason | J1: Fee % | K1: Fee Amount | L1: Net Amount
A2: TXN00837 | B2: 45474.097 | C2: DE | D2: EUR | E2: Checkout.com | F2: Debit Card | G2: 2921.32 | H2: Success | J2: 1.9 | K2: 55.51 | L2: 2865.81
A3: TXN00971 | B3: 45474.882 | C3: FR | D3: EUR | E3: Checkout.com | F3: Credit Card | G3: 4036.01 | H3: Success | J3: 1.9 | K3: 76.68 | L3: 3959.33
A4: TXN00486 | B4: 45475.61 | C4: IT | D4: EUR | E4: Stripe | F4: E-Wallet | G4: 4076.67 | H4: Success | J4: 2.9 | K4: 118.22 | L4: 3958.45
A5: TXN00945 | B5: 45475.879 | C5: PL | D5: PLN | E5: Checkout.com | F5: Debit Card | G5: 2453.22 | H5: Failed | I5: Technical Error | J5: 1.9 | K5: 0 | L5: 0
A6: TXN00481 | B6: 45475.935 | C6: IT | D6: EUR | E6: Adyen | F6: Credit Card | G6: 2745.21 | H6: Success | J6: 2.1 | K6: 57.65 | L6: 2687.56
A7: TXN00747 | B7: 45476.548 | C7: IT | D7: EUR | E7: Adyen | F7: Debit Card | G7: 67.9 | H7: Success | J7: 2.1 | K7: 1.43 | L7: 66.47
A8: TXN00149 | B8: 45477.692 | C8: GB | D8: GBP | E8: Worldpay | F8: Crypto | G8: 1115.53 | H8: Pending | J8: 2.5 | K8: 0 | L8: 0
A9: TXN00556 | B9: 45477.823 | C9: GB | D9: GBP | E9: Adyen | F9: Bank Transfer | G9: 4057.75 | H9: Success | J9: 2.1 | K9: 85.21 | L9: 3972.54
A10: TXN00499 | B10: 45478.078 | C10: ES | D10: EUR | E10: Worldpay | F10: E-Wallet | G10: 2805.15 | H10: Pending | J10: 2.5 | K10: 0 | L10: 0
A11: TXN00326 | B11: 45478.166 | C11: NO | D11: NOK | E11: Adyen | F11: Crypto | G11: 4986.35 | H11: Success | J11: 2.1 | K11: 104.71 | L11: 4881.64
A12: TXN00898 | B12: 45478.59 | C12: ES | D12: EUR | E12: Adyen | F12: E-Wallet | G12: 4222.17 | H12: Failed | I12: Fraud Suspected | J12: 2.1 | K12: 0 | L12: 0
A13: TXN00240 | B13: 45479.059 | C13: DE | D13: EUR | E13: Checkout.com | F13: Crypto | G13: 981.33 | H13: Pending | J13: 1.9 | K13: 0 | L13: 0
A14: TXN00135 | B14: 45479.118 | C14: CY | D14: EUR | E14: Stripe | F14: E-Wallet | G14: 2687.5 | H14: Failed | I14: Fraud Suspected | J14: 2.9 | K14: 0 | L14: 0
A15: TXN00597 | B15: 45479.23 | C15: CY | D15: EUR | E15: Adyen | F15: Bank Transfer | G15: 3506.56 | H15: Success | J15: 2.1 | K15: 73.64 | L15: 3432.92
A16: TXN00664 | B16: 45479.467 | C16: PL | D16: PLN | E16: PaySafe | F16: Crypto | G16: 3280.5 | H16: Success | J16: 3.2 | K16: 104.98 | L16: 3175.52
A17: TXN00374 | B17: 45479.738 | C17: FR | D17: EUR | E17: Worldpay | F17: Credit Card | G17: 93.28 | H17: Success | J17: 2.5 | K17: 2.33 | L17: 90.95
A18: TXN00389 | B18: 45480.772 | C18: ES | D18: EUR | E18: Checkout.com | F18: Debit Card | G18: 761.33 | H18: Failed | I18: Insufficient Funds | J18: 1.9 | K18: 0 | L18: 0
A19: TXN00192 | B19: 45480.9 | C19: NL | D19: EUR | E19: Worldpay | F19: E-Wallet | G19: 3892.84 | H19: Pending | J19: 2.5 | K19: 0 | L19: 0
A20: TXN00290 | B20: 45481.107 | C20: ES | D20: EUR | E20: Stripe | F20: E-Wallet | G20: 1892.07 | H20: Pending | J20: 2.9 | K20: 0 | L20: 0
A21: TXN00572 | B21: 45481.733 | C21: NL | D21: EUR | E21: PaySafe | F21: E-Wallet | G21: 2892.48 | H21: Failed | I21: Card Declined | J21: 3.2 | K21: 0 | L21: 0
A22: TXN00182 | B22: 45482.392 | C22: CY | D22: EUR | E22: PaySafe | F22: Crypto | G22: 271.3 | H22: Success | J22: 3.2 | K22: 8.68 | L22: 262.62
A23: TXN00829 | B23: 45482.409 | C23: DE | D23: EUR | E23: Adyen | F23: E-Wallet | G23: 1429.07 | H23: Success | J23: 2.1 | K23: 30.01 | L23: 1399.06
A24: TXN00998 | B24: 45483.387 | C24: NL | D24: EUR | E24: Stripe | F24: Debit Card | G24: 719.28 | H24: Pending | J24: 2.9 | K24: 0 | L24: 0
A25: TXN00305 | B25: 45483.52 | C25: NO | D25: NOK | E25: Adyen | F25: Debit Card | G25: 1506.87 | H25: Success | J25: 2.1 | K25: 31.64 | L25: 1475.23
A26: TXN00939 | B26: 45483.791 | C26: GB | D26: GBP | E26: PaySafe | F26: Debit Card | G26: 154.08 | H26: Failed | I26: Technical Error | J26: 3.2 | K26: 0 | L26: 0
A27: TXN00252 | B27: 45484.424 | C27: NL | D27: EUR | E27: Checkout.com | F27: E-Wallet | G27: 2735.9 | H27: Success | J27: 1.9 | K27: 51.98 | L27: 2683.92
A28: TXN00553 | B28: 45484.85 | C28: PL | D28: PLN | E28: Checkout.com | F28: Credit Card | G28: 2588.15 | H28: Failed | I28: Card Declined | J28: 1.9 | K28: 0 | L28: 0
A29: TXN00519 | B29: 45485.06 | C29: IT | D29: EUR | E29: Checkout.com | F29: E-Wallet | G29: 659.03 | H29: Pending | J29: 1.9 | K29: 0 | L29: 0
A30: TXN00419 | B30: 45485.407 | C30: IT | D30: EUR | E30: Adyen | F30: Debit Card | G30: 3646.87 | H30: Pending | J30: 2.1 | K30: 0 | L30: 0
A31: TXN00704 | B31: 45486.117 | C31: CY | D31: EUR | E31: Checkout.com | F31: Credit Card | G31: 1471.24 | H31: Success | J31: 1.9 | K31: 27.95 | L31: 1443.29
A32: TXN00672 | B32: 45486.698 | C32: GB | D32: GBP | E32: PaySafe | F32: Bank Transfer | G32: 4335.2 | H32: Pending | J32: 3.2 | K32: 0 | L32: 0
A33: TXN00765 | B33: 45486.906 | C33: CY | D33: EUR | E33: Worldpay | F33: E-Wallet | G33: 734.3 | H33: Failed | I33: Insufficient Funds | J33: 2.5 | K33: 0 | L33: 0
A34: TXN00775 | B34: 45487.515 | C34: DE | D34: EUR | E34: PaySafe | F34: E-Wallet | G34: 897.87 | H34: Success | J34: 3.2 | K34: 28.73 | L34: 869.14
A35: TXN00746 | B35: 45487.565 | C35: ES | D35: EUR | E35: Adyen | F35: Bank Transfer | G35: 703.95 | H35: Pending | J35: 2.1 | K35: 0 | L35: 0
A36: TXN00278 | B36: 45487.622 | C36: CY | D36: EUR | E36: Worldpay | F36: Credit Card | G36: 3416.82 | H36: Pending | J36: 2.5 | K36: 0 | L36: 0
A37: TXN00729 | B37: 45488.045 | C37: CY | D37: EUR | E37: Worldpay | F37: Debit Card | G37: 3526.34 | H37: Pending | J37: 2.5 | K37: 0 | L37: 0
A38: TXN00563 | B38: 45489.171 | C38: DE | D38: EUR | E38: Adyen | F38: Crypto | G38: 4299.36 | H38: Pending | J38: 2.1 | K38: 0 | L38: 0
A39: TXN00869 | B39: 45489.395 | C39: NO | D39: NOK | E39: PaySafe | F39: Bank Transfer | G39: 1137.11 | H39: Failed | I39: Fraud Suspected | J39: 3.2 | K39: 0 | L39: 0
A40: TXN00805 | B40: 45490.464 | C40: NL | D40: EUR | E40: Adyen | F40: E-Wallet | G40: 4878.02 | H40: Success | J40: 2.1 | K40: 102.44 | L40: 4775.58
A41: TXN00516 | B41: 45490.576 | C41: PL | D41: PLN | E41: Checkout.com | F41: Credit Card | G41: 74.7 | H41: Success | J41: 1.9 | K41: 1.42 | L41: 73.28
A42: TXN00440 | B42: 45490.726 | C42: SE | D42: SEK | E42: PaySafe | F42: E-Wallet | G42: 2603.24 | H42: Success | J42: 3.2 | K42: 83.3 | L42: 2519.94
A43: TXN00070 | B43: 45491.446 | C43: CY | D43: EUR | E43: Adyen | F43: Bank Transfer | G43: 4598.51 | H43: Pending | J43: 2.1 | K43: 0 | L43: 0
A44: TXN00204 | B44: 45491.626 | C44: CY | D44: EUR | E44: PaySafe | F44: E-Wallet | G44: 3739.11 | H44: Success | J44: 3.2 | K44: 119.65 | L44: 3619.46
A45: TXN00985 | B45: 45491.99 | C45: FR | D45: EUR | E45: Checkout.com | F45: Crypto | G45: 1426.8 | H45: Success | J45: 1.9 | K45: 27.11 | L45: 1399.69
A46: TXN00547 | B46: 45492.331 | C46: NO | D46: NOK | E46: PaySafe | F46: Debit Card | G46: 2328.86 | H46: Pending | J46: 3.2 | K46: 0 | L46: 0
A47: TXN00883 | B47: 45492.355 | C47: NO | D47: NOK | E47: Worldpay | F47: Crypto | G47: 3385.67 | H47: Success | J47: 2.5 | K47: 84.64 | L47: 3301.03
A48: TXN00534 | B48: 45492.721 | C48: FR | D48: EUR | E48: PaySafe | F48: E-Wallet | G48: 4787.38 | H48: Success | J48: 3.2 | K48: 153.2 | L48: 4634.18
A49: TXN00503 | B49: 45493.27 | C49: ES | D49: EUR | E49: PaySafe | F49: Credit Card | G49: 3788.18 | H49: Success | J49: 3.2 | K49: 121.22 | L49: 3666.96
A50: TXN00071 | B50: 45493.775 | C50: DE | D50: EUR | E50: Stripe | F50: Bank Transfer | G50: 687.14 | H50: Failed | I50: Card Declined | J50: 2.9 | K50: 0 | L50: 0
A51: TXN00871 | B51: 45494.606 | C51: GB | D51: GBP | E51: Stripe | F51: Debit Card | G51: 1980.11 | H51: Pending | J51: 2.9 | K51: 0 | L51: 0
A52: TXN00651 | B52: 45495.032 | C52: DE | D52: EUR | E52: PaySafe | F52: Crypto | G52: 91.35 | H52: Success | J52: 3.2 | K52: 2.92 | L52: 88.43
A53: TXN00293 | B53: 45495.316 | C53: PL | D53: PLN | E53: PaySafe | F53: Bank Transfer | G53: 2336.59 | H53: Success | J53: 3.2 | K53: 74.77 | L53: 2261.82
A54: TXN00593 | B54: 45495.325 | C54: NO | D54: NOK | E54: Adyen | F54: Credit Card | G54: 2633.42 | H54: Failed | I54: Technical Error | J54: 2.1 | K54: 0 | L54: 0
A55: TXN00548 | B55: 45495.481 | C55: DE | D55: EUR | E55: Adyen | F55: Crypto | G55: 3423.97 | H55: Pending | J55: 2.1 | K55: 0 | L55: 0
A56: TXN00262 | B56: 45495.633 | C56: IT | D56: EUR | E56: Stripe | F56: Credit Card | G56: 1498.98 | H56: Pending | J56: 2.9 | K56: 0 | L56: 0
A57: TXN00451 | B57: 45495.874 | C57: GB | D57: GBP | E57: Stripe | F57: Debit Card | G57: 1868.61 | H57: Pending | J57: 2.9 | K57: 0 | L57: 0
A58: TXN00387 | B58: 45497.122 | C58: NL | D58: EUR | E58: PaySafe | F58: E-Wallet | G58: 1643.23 | H58: Pending | J58: 3.2 | K58: 0 | L58: 0
A59: TXN00598 | B59: 45497.353 | C59: FR | D59: EUR | E59: Checkout.com | F59: Debit Card | G59: 4896.57 | H59: Success | J59: 1.9 | K59: 93.03 | L59: 4803.54
A60: TXN00487 | B60: 45497.52 | C60: IT | D60: EUR | E60: Worldpay | F60: Bank Transfer | G60: 4001.5 | H60: Success | J60: 2.5 | K60: 100.04 | L60: 3901.46
A61: TXN00496 | B61: 45498.295 | C61: NL | D61: EUR | E61: Worldpay | F61: Crypto | G61: 2246.01 | H61: Failed | I61: Technical Error | J61: 2.5 | K61: 0 | L61: 0
A62: TXN00470 | B62: 45498.562 | C62: CY | D62: EUR | E62: Stripe | F62: Credit Card | G62: 2673.58 | H62: Success | J62: 2.9 | K62: 77.53 | L62: 2596.05
A63: TXN00786 | B63: 45499.134 | C63: SE | D63: SEK | E63: Worldpay | F63: Crypto | G63: 753.28 | H63: Pending | J63: 2.5 | K63: 0 | L63: 0
A64: TXN00900 | B64: 45499.297 | C64: FR | D64: EUR | E64: Adyen | F64: Credit Card | G64: 1235.48 | H64: Success | J64: 2.1 | K64: 25.95 | L64: 1209.53
A65: TXN00338 | B65: 45499.841 | C65: FR | D65: EUR | E65: Worldpay | F65: Bank Transfer | G65: 155.67 | H65: Pending | J65: 2.5 | K65: 0 | L65: 0
A66: TXN00347 | B66: 45501.897 | C66: CY | D66: EUR | E66: Worldpay | F66: Bank Transfer | G66: 844.59 | H66: Pending | J66: 2.5 | K66: 0 | L66: 0
A67: TXN00355 | B67: 45502.053 | C67: FR | D67: EUR | E67: Adyen | F67: Debit Card | G67: 739.75 | H67: Success | J67: 2.1 | K67: 15.53 | L67: 724.22
A68: TXN00770 | B68: 45502.148 | C68: GB | D68: GBP | E68: Worldpay | F68: E-Wallet | G68: 1104.89 | H68: Success | J68: 2.5 | K68: 27.62 | L68: 1077.27
A69: TXN00608 | B69: 45503.216 | C69: DE | D69: EUR | E69: Adyen | F69: Debit Card | G69: 3313.49 | H69: Success | J69: 2.1 | K69: 69.58 | L69: 3243.91
A70: TXN00914 | B70: 45503.448 | C70: CY | D70: EUR | E70: Stripe | F70: Debit Card | G70: 3495.43 | H70: Pending | J70: 2.9 | K70: 0 | L70: 0
A71: TXN00424 | B71: 45503.664 | C71: CY | D71: EUR | E71: PaySafe | F71: Crypto | G71: 1882.98 | H71: Failed | I71: Expired Card | J71: 3.2 | K71: 0 | L71: 0
A72: TXN00196 | B72: 45504.059 | C72: SE | D72: SEK | E72: PaySafe | F72: Debit Card | G72: 1936.97 | H72: Success | J72: 3.2 | K72: 61.98 | L72: 1874.99
A73: TXN00271 | B73: 45504.941 | C73: NL | D73: EUR | E73: Checkout.com | F73: Debit Card | G73: 3811.68 | H73: Pending | J73: 1.9 | K73: 0 | L73: 0
A74: TXN00938 | B74: 45505.094 | C74: NL | D74: EUR | E74: Stripe | F74: E-Wallet | G74: 139.55 | H74: Success | J74: 2.9 | K74: 4.05 | L74: 135.5
A75: TXN00677 | B75: 45505.317 | C75: FR | D75: EUR | E75: Worldpay | F75: E-Wallet | G75: 4549.58 | H75: Success | J75: 2.5 | K75: 113.74 | L75: 4435.84
A76: TXN00856 | B76: 45505.624 | C76: GB | D76: GBP | E76: Stripe | F76: Debit Card | G76: 4617.81 | H76: Failed | I76: Fraud Suspected | J76: 2.9 | K76: 0 | L76: 0
A77: TXN00797 | B77: 45506.024 | C77: ES | D77: EUR | E77: Adyen | F77: Credit Card | G77: 4933.15 | H77: Success | J77: 2.1 | K77: 103.6 | L77: 4829.55
A78: TXN00925 | B78: 45506.226 | C78: FR | D78: EUR | E78: Stripe | F78: E-Wallet | G78: 4880.88 | H78: Success | J78: 2.9 | K78: 141.55 | L78: 4739.33
A79: TXN00807 | B79: 45506.242 | C79: PL | D79: PLN | E79: Adyen | F79: E-Wallet | G79: 3022.14 | H79: Pending | J79: 2.1 | K79: 0 | L79: 0
A80: TXN00407 | B80: 45506.278 | C80: SE | D80: SEK | E80: Adyen | F80: Crypto | G80: 3976.28 | H80: Failed | I80: Fraud Suspected | J80: 2.1 | K80: 0 | L80: 0
A81: TXN00461 | B81: 45506.517 | C81: DE | D81: EUR | E81: Checkout.com | F81: Crypto | G81: 4081.91 | H81: Success | J81: 1.9 | K81: 77.56 | L81: 4004.35
A82: TXN00982 | B82: 45506.539 | C82: SE | D82: SEK | E82: PaySafe | F82: E-Wallet | G82: 4547.06 | H82: Success | J82: 3.2 | K82: 145.51 | L82: 4401.55
A83: TXN00344 | B83: 45506.797 | C83: NO | D83: NOK | E83: Worldpay | F83: Bank Transfer | G83: 936.91 | H83: Pending | J83: 2.5 | K83: 0 | L83: 0
A84: TXN00073 | B84: 45507.37 | C84: GB | D84: GBP | E84: Worldpay | F84: Credit Card | G84: 3747.63 | H84: Success | J84: 2.5 | K84: 93.69 | L84: 3653.94
A85: TXN00566 | B85: 45507.497 | C85: DE | D85: EUR | E85: Checkout.com | F85: Bank Transfer | G85: 1155.14 | H85: Failed | I85: Technical Error | J85: 1.9 | K85: 0 | L85: 0
A86: TXN00512 | B86: 45508.023 | C86: GB | D86: GBP | E86: Stripe | F86: Bank Transfer | G86: 735.18 | H86: Success | J86: 2.9 | K86: 21.32 | L86: 713.86
A87: TXN00456 | B87: 45508.537 | C87: PL | D87: PLN | E87: Worldpay | F87: E-Wallet | G87: 1098.86 | H87: Success | J87: 2.5 | K87: 27.47 | L87: 1071.39
A88: TXN00027 | B88: 45508.562 | C88: DE | D88: EUR | E88: Stripe | F88: Credit Card | G88: 2019.08 | H88: Success | J88: 2.9 | K88: 58.55 | L88: 1960.53
A89: TXN00376 | B89: 45508.934 | C89: GB | D89: GBP | E89: Checkout.com | F89: Crypto | G89: 3084.07 | H89: Success | J89: 1.9 | K89: 58.6 | L89: 3025.47
A90: TXN00100 | B90: 45509.149 | C90: ES | D90: EUR | E90: Adyen | F90: E-Wallet | G90: 4134.89 | H90: Success | J90: 2.1 | K90: 86.83 | L90: 4048.06
A91: TXN00431 | B91: 45510.096 | C91: NO | D91: NOK | E91: Worldpay | F91: Debit Card | G91: 493.96 | H91: Success | J91: 2.5 | K91: 12.35 | L91: 481.61
A92: TXN00687 | B92: 45510.534 | C92: DE | D92: EUR | E92: Checkout.com | F92: Bank Transfer | G92: 3603.8 | H92: Failed | I92: Expired Card | J92: 1.9 | K92: 0 | L92: 0
A93: TXN00707 | B93: 45510.829 | C93: PL | D93: PLN | E93: PaySafe | F93: Crypto | G93: 2879.96 | H93: Pending | J93: 3.2 | K93: 0 | L93: 0
A94: TXN00870 | B94: 45511.287 | C94: GB | D94: GBP | E94: Worldpay | F94: E-Wallet | G94: 904.69 | H94: Failed | I94: Insufficient Funds | J94: 2.5 | K94: 0 | L94: 0
A95: TXN00160 | B95: 45511.742 | C95: NO | D95: NOK | E95: Checkout.com | F95: Crypto | G95: 141.01 | H95: Success | J95: 1.9 | K95: 2.68 | L95: 138.33
A96: TXN00364 | B96: 45511.837 | C96: GB | D96: GBP | E96: Stripe | F96: Debit Card | G96: 2389.27 | H96: Success | J96: 2.9 | K96: 69.29 | L96: 2319.98
A97: TXN00881 | B97: 45512.18 | C97: CY | D97: EUR | E97: Worldpay | F97: Credit Card | G97: 2848.59 | H97: Failed | I97: Expired Card | J97: 2.5 | K97: 0 | L97: 0
A98: TXN00154 | B98: 45512.622 | C98: ES | D98: EUR | E98: Worldpay | F98: E-Wallet | G98: 4138.82 | H98: Failed | I98: Technical Error | J98: 2.5 | K98: 0 | L98: 0
A99: TXN00428 | B99: 45512.84 | C99: NO | D99: NOK | E99: Worldpay | F99: Debit Card | G99: 277.24 | H99: Success | J99: 2.5 | K99: 6.93 | L99: 270.31
A100: TXN00314 | B100: 45513.238 | C100: NO | D100: NOK | E100: Worldpay | F100: Credit Card | G100: 3863.12 | H100: Success | J100: 2.5 | K100: 96.58 | L100: 3766.54
...

Sheet FX Rates
A1: FX Rates (to EUR) - 2024 Annual Average
A2: Currency | B2: Rate to EUR | C2: Source
A3: SEK | B3: 0.0874 | C3: ECB (2024 Avg)
A4: NOK | B4: 0.086 | C4: ECB (2024 Avg)
A5: EUR | B5: 1 | C5: ECB (2024 Avg)
A6: GBP | B6: 1.1802 | C6: ECB (2024 Avg)
A7: PLN | B7: 0.2327 | C7: ECB (2024 Avg)

Sheet Raw_Data_Combined
A1: Transaction ID | B1: Date & Time | C1: GEO | D1: Currency | E1: PSP Provider | F1: Payment Method | G1: Amount | H1: Status | I1: Decline Reason | J1: Fee % | K1: Exchange Rate to EUR | L1: Fee Amount EUR | M1: Net Amount EUR | N1: Gross Amount EUR | O1: Month Name
A2: TXN00108 | B2: 45292.913 | C2: SE | D2: SEK | E2: Worldpay | F2: Bank Transfer | G2: 280.48 | H2: Pending | J2: 2.5 | K2: 0.0874 | L2: 0 | M2: 0 | N2: 0 | O2: January
A3: TXN00929 | B3: 45294.356 | C3: NO | D3: NOK | E3: Worldpay | F3: E-Wallet | G3: 4887.84 | H3: Success | J3: 2.5 | K3: 0.086 | L3: 10.5092 | M3: 409.84504 | N3: 420.35424 | O3: January
A4: TXN00542 | B4: 45294.427 | C4: ES | D4: EUR | E4: Worldpay | F4: E-Wallet | G4: 4202.15 | H4: Success | J4: 2.5 | K4: 1 | L4: 105.05 | M4: 4097.1 | N4: 4202.15 | O4: January
A5: TXN00520 | B5: 45294.437 | C5: FR | D5: EUR | E5: Stripe | F5: Debit Card | G5: 4643.85 | H5: Pending | J5: 2.9 | K5: 1 | L5: 0 | M5: 0 | N5: 0 | O5: January
A6: TXN00794 | B6: 45295.008 | C6: GB | D6: GBP | E6: Checkout.com | F6: E-Wallet | G6: 2086.95 | H6: Failed | I6: Card Declined | J6: 1.9 | K6: 1.1802 | L6: 0 | M6: 0 | N6: 0 | O6: January
A7: TXN00712 | B7: 45295.155 | C7: PL | D7: PLN | E7: PaySafe | F7: Bank Transfer | G7: 3624.74 | H7: Pending | J7: 3.2 | K7: 0.2327 | L7: 0 | M7: 0 | N7: 0 | O7: January
A8: TXN00652 | B8: 45295.385 | C8: ES | D8: EUR | E8: PaySafe | F8: Credit Card | G8: 3859.9 | H8: Success | J8: 3.2 | K8: 1 | L8: 123.52 | M8: 3736.38 | N8: 3859.9 | O8: January
A9: TXN00600 | B9: 45296.226 | C9: NL | D9: EUR | E9: Adyen | F9: Crypto | G9: 2674.57 | H9: Success | J9: 2.1 | K9: 1 | L9: 56.17 | M9: 2618.4 | N9: 2674.57 | O9: January
A10: TXN00388 | B10: 45296.467 | C10: IT | D10: EUR | E10: Checkout.com | F10: E-Wallet | G10: 3700.48 | H10: Success | J10: 1.9 | K10: 1 | L10: 70.31 | M10: 3630.17 | N10: 3700.48 | O10: January
A11: TXN00617 | B11: 45296.577 | C11: IT | D11: EUR | E11: Checkout.com | F11: Debit Card | G11: 3985.87 | H11: Pending | J11: 1.9 | K11: 1 | L11: 0 | M11: 0 | N11: 0 | O11: January
A12: TXN00494 | B12: 45297.874 | C12: FR | D12: EUR | E12: Checkout.com | F12: Bank Transfer | G12: 4260.84 | H12: Success | J12: 1.9 | K12: 1 | L12: 80.96 | M12: 4179.88 | N12: 4260.84 | O12: January
A13: TXN00643 | B13: 45298.278 | C13: NL | D13: EUR | E13: Stripe | F13: Bank Transfer | G13: 4007.09 | H13: Success | J13: 2.9 | K13: 1 | L13: 116.21 | M13: 3890.88 | N13: 4007.09 | O13: January
A14: TXN00630 | B14: 45299.243 | C14: IT | D14: EUR | E14: Checkout.com | F14: Credit Card | G14: 1985.08 | H14: Success | J14: 1.9 | K14: 1 | L14: 37.72 | M14: 1947.36 | N14: 1985.08 | O14: January
A15: TXN00292 | B15: 45299.291 | C15: ES | D15: EUR | E15: Stripe | F15: Bank Transfer | G15: 4573.06 | H15: Pending | J15: 2.9 | K15: 1 | L15: 0 | M15: 0 | N15: 0 | O15: January
A16: TXN00726 | B16: 45299.816 | C16: SE | D16: SEK | E16: Stripe | F16: Debit Card | G16: 2717.22 | H16: Pending | J16: 2.9 | K16: 0.0874 | L16: 0 | M16: 0 | N16: 0 | O16: January
A17: TXN00265 | B17: 45299.973 | C17: IT | D17: EUR | E17: Checkout.com | F17: Debit Card | G17: 885.72 | H17: Failed | I17: Technical Error | J17: 1.9 | K17: 1 | L17: 0 | M17: 0 | N17: 0 | O17: January
A18: TXN00282 | B18: 45300.301 | C18: GB | D18: GBP | E18: Stripe | F18: Crypto | G18: 177.55 | H18: Pending | J18: 2.9 | K18: 1.1802 | L18: 0 | M18: 0 | N18: 0 | O18: January
A19: TXN00860 | B19: 45301.658 | C19: CY | D19: EUR | E19: Stripe | F19: Debit Card | G19: 548.01 | H19: Pending | J19: 2.9 | K19: 1 | L19: 0 | M19: 0 | N19: 0 | O19: January
A20: TXN00545 | B20: 45301.694 | C20: DE | D20: EUR | E20: Checkout.com | F20: Crypto | G20: 2031.62 | H20: Pending | J20: 1.9 | K20: 1 | L20: 0 | M20: 0 | N20: 0 | O20: January
A21: TXN00896 | B21: 45301.865 | C21: SE | D21: SEK | E21: Adyen | F21: Crypto | G21: 2501.03 | H21: Failed | I21: Fraud Suspected | J21: 2.1 | K21: 0.0874 | L21: 0 | M21: 0 | N21: 0 | O21: January
A22: TXN00920 | B22: 45302.041 | C22: SE | D22: SEK | E22: Checkout.com | F22: Debit Card | G22: 4535.16 | H22: Failed | I22: Card Declined | J22: 1.9 | K22: 0.0874 | L22: 0 | M22: 0 | N22: 0 | O22: January
A23: TXN00426 | B23: 45302.428 | C23: GB | D23: GBP | E23: Stripe | F23: E-Wallet | G23: 858.82 | H23: Failed | I23: Card Declined | J23: 2.9 | K23: 1.1802 | L23: 0 | M23: 0 | N23: 0 | O23: January
A24: TXN00634 | B24: 45302.933 | C24: PL | D24: PLN | E24: Adyen | F24: E-Wallet | G24: 4494.33 | H24: Failed | I24: Technical Error | J24: 2.1 | K24: 0.2327 | L24: 0 | M24: 0 | N24: 0 | O24: January
A25: TXN00280 | B25: 45303.395 | C25: SE | D25: SEK | E25: Worldpay | F25: Crypto | G25: 1902.59 | H25: Success | J25: 2.5 | K25: 0.0874 | L25: 4.156744 | M25: 162.12962 | N25: 166.28637 | O25: January
A26: TXN00724 | B26: 45303.783 | C26: IT | D26: EUR | E26: Adyen | F26: E-Wallet | G26: 1010.77 | H26: Success | J26: 2.1 | K26: 1 | L26: 21.23 | M26: 989.54 | N26: 1010.77 | O26: January
A27: TXN00047 | B27: 45304.241 | C27: PL | D27: PLN | E27: Worldpay | F27: Debit Card | G27: 1341.36 | H27: Success | J27: 2.5 | K27: 0.2327 | L27: 7.802431 | M27: 304.33204 | N27: 312.13447 | O27: January
A28: TXN00526 | B28: 45304.703 | C28: PL | D28: PLN | E28: Checkout.com | F28: Crypto | G28: 2233.33 | H28: Success | J28: 1.9 | K28: 0.2327 | L28: 9.873461 | M28: 509.82243 | N28: 519.69589 | O28: January
A29: TXN00049 | B29: 45304.883 | C29: CY | D29: EUR | E29: PaySafe | F29: E-Wallet | G29: 4323.12 | H29: Success | J29: 3.2 | K29: 1 | L29: 138.34 | M29: 4184.78 | N29: 4323.12 | O29: January
A30: TXN00848 | B30: 45306.158 | C30: IT | D30: EUR | E30: Worldpay | F30: Credit Card | G30: 2998.47 | H30: Success | J30: 2.5 | K30: 1 | L30: 74.96 | M30: 2923.51 | N30: 2998.47 | O30: January
A31: TXN00404 | B31: 45307.53 | C31: CY | D31: EUR | E31: Adyen | F31: E-Wallet | G31: 1081.43 | H31: Success | J31: 2.1 | K31: 1 | L31: 22.71 | M31: 1058.72 | N31: 1081.43 | O31: January
A32: TXN00980 | B32: 45307.59 | C32: DE | D32: EUR | E32: Checkout.com | F32: Credit Card | G32: 433.04 | H32: Success | J32: 1.9 | K32: 1 | L32: 8.23 | M32: 424.81 | N32: 433.04 | O32: January
A33: TXN00641 | B33: 45308.254 | C33: NL | D33: EUR | E33: Adyen | F33: Credit Card | G33: 168.77 | H33: Failed | I33: Technical Error | J33: 2.1 | K33: 1 | L33: 0 | M33: 0 | N33: 0 | O33: January
A34: TXN00011 | B34: 45308.434 | C34: IT | D34: EUR | E34: Stripe | F34: Debit Card | G34: 4566.55 | H34: Pending | J34: 2.9 | K34: 1 | L34: 0 | M34: 0 | N34: 0 | O34: January
A35: TXN00879 | B35: 45308.581 | C35: GB | D35: GBP | E35: Worldpay | F35: Bank Transfer | G35: 1579.65 | H35: Failed | I35: Technical Error | J35: 2.5 | K35: 1.1802 | L35: 0 | M35: 0 | N35: 0 | O35: January
A36: TXN00996 | B36: 45308.965 | C36: SE | D36: SEK | E36: PaySafe | F36: Credit Card | G36: 3011.99 | H36: Failed | I36: Insufficient Funds | J36: 3.2 | K36: 0.0874 | L36: 0 | M36: 0 | N36: 0 | O36: January
A37: TXN00215 | B37: 45309.169 | C37: ES | D37: EUR | E37: PaySafe | F37: E-Wallet | G37: 1920.44 | H37: Pending | J37: 3.2 | K37: 1 | L37: 0 | M37: 0 | N37: 0 | O37: January
A38: TXN00627 | B38: 45309.27 | C38: GB | D38: GBP | E38: Checkout.com | F38: Debit Card | G38: 2369.4 | H38: Success | J38: 1.9 | K38: 1.1802 | L38: 53.132604 | M38: 2743.2333 | N38: 2796.3659 | O38: January
A39: TXN00612 | B39: 45309.89 | C39: PL | D39: PLN | E39: Worldpay | F39: Bank Transfer | G39: 4875.16 | H39: Pending | J39: 2.5 | K39: 0.2327 | L39: 0 | M39: 0 | N39: 0 | O39: January
A40: TXN00118 | B40: 45310.189 | C40: NO | D40: NOK | E40: PaySafe | F40: Credit Card | G40: 4372.21 | H40: Failed | I40: Insufficient Funds | J40: 3.2 | K40: 0.086 | L40: 0 | M40: 0 | N40: 0 | O40: January
A41: TXN00207 | B41: 45310.383 | C41: DE | D41: EUR | E41: Adyen | F41: Credit Card | G41: 1584.82 | H41: Success | J41: 2.1 | K41: 1 | L41: 33.28 | M41: 1551.54 | N41: 1584.82 | O41: January
A42: TXN00330 | B42: 45310.489 | C42: SE | D42: SEK | E42: Checkout.com | F42: Credit Card | G42: 555.75 | H42: Success | J42: 1.9 | K42: 0.0874 | L42: 0.922944 | M42: 47.649606 | N42: 48.57255 | O42: January
A43: TXN00963 | B43: 45310.642 | C43: NL | D43: EUR | E43: Checkout.com | F43: Crypto | G43: 3625.82 | H43: Failed | I43: Card Declined | J43: 1.9 | K43: 1 | L43: 0 | M43: 0 | N43: 0 | O43: January
A44: TXN00546 | B44: 45310.719 | C44: SE | D44: SEK | E44: Checkout.com | F44: Bank Transfer | G44: 3273 | H44: Success | J44: 1.9 | K44: 0.0874 | L44: 5.435406 | M44: 280.62479 | N44: 286.0602 | O44: January
A45: TXN00385 | B45: 45310.744 | C45: CY | D45: EUR | E45: Adyen | F45: E-Wallet | G45: 1248.83 | H45: Success | J45: 2.1 | K45: 1 | L45: 26.23 | M45: 1222.6 | N45: 1248.83 | O45: January
A46: TXN00048 | B46: 45311.635 | C46: ES | D46: EUR | E46: Worldpay | F46: E-Wallet | G46: 1532.9 | H46: Success | J46: 2.5 | K46: 1 | L46: 38.32 | M46: 1494.58 | N46: 1532.9 | O46: January
A47: TXN00181 | B47: 45312.323 | C47: NL | D47: EUR | E47: Worldpay | F47: Crypto | G47: 2618.51 | H47: Success | J47: 2.5 | K47: 1 | L47: 65.46 | M47: 2553.05 | N47: 2618.51 | O47: January
A48: TXN00550 | B48: 45312.325 | C48: NL | D48: EUR | E48: Adyen | F48: Credit Card | G48: 1329.14 | H48: Success | J48: 2.1 | K48: 1 | L48: 27.91 | M48: 1301.23 | N48: 1329.14 | O48: January
A49: TXN00525 | B49: 45312.914 | C49: PL | D49: PLN | E49: Worldpay | F49: Credit Card | G49: 1935.52 | H49: Pending | J49: 2.5 | K49: 0.2327 | L49: 0 | M49: 0 | N49: 0 | O49: January
A50: TXN00256 | B50: 45313.406 | C50: GB | D50: GBP | E50: PaySafe | F50: Bank Transfer | G50: 3283.3 | H50: Failed | I50: Card Declined | J50: 3.2 | K50: 1.1802 | L50: 0 | M50: 0 | N50: 0 | O50: January
A51: TXN00403 | B51: 45313.585 | C51: FR | D51: EUR | E51: Checkout.com | F51: Bank Transfer | G51: 4110.21 | H51: Failed | I51: Technical Error | J51: 1.9 | K51: 1 | L51: 0 | M51: 0 | N51: 0 | O51: January
A52: TXN00631 | B52: 45313.785 | C52: NL | D52: EUR | E52: Checkout.com | F52: Debit Card | G52: 1863.28 | H52: Success | J52: 1.9 | K52: 1 | L52: 35.4 | M52: 1827.88 | N52: 1863.28 | O52: January
A53: TXN00384 | B53: 45314.01 | C53: DE | D53: EUR | E53: Worldpay | F53: E-Wallet | G53: 1921.07 | H53: Success | J53: 2.5 | K53: 1 | L53: 48.03 | M53: 1873.04 | N53: 1921.07 | O53: January
A54: TXN00811 | B54: 45314.062 | C54: SE | D54: SEK | E54: Stripe | F54: Bank Transfer | G54: 2660.3 | H54: Failed | I54: Insufficient Funds | J54: 2.9 | K54: 0.0874 | L54: 0 | M54: 0 | N54: 0 | O54: January
A55: TXN00491 | B55: 45315.094 | C55: PL | D55: PLN | E55: Stripe | F55: Crypto | G55: 3839.97 | H55: Pending | J55: 2.9 | K55: 0.2327 | L55: 0 | M55: 0 | N55: 0 | O55: January
A56: TXN00973 | B56: 45315.72 | C56: FR | D56: EUR | E56: Checkout.com | F56: Crypto | G56: 3350.73 | H56: Success | J56: 1.9 | K56: 1 | L56: 63.66 | M56: 3287.07 | N56: 3350.73 | O56: January
A57: TXN00230 | B57: 45315.867 | C57: NO | D57: NOK | E57: PaySafe | F57: Debit Card | G57: 3837.13 | H57: Failed | I57: Expired Card | J57: 3.2 | K57: 0.086 | L57: 0 | M57: 0 | N57: 0 | O57: January
A58: TXN00999 | B58: 45316.414 | C58: IT | D58: EUR | E58: Adyen | F58: Debit Card | G58: 4097.43 | H58: Failed | I58: Insufficient Funds | J58: 2.1 | K58: 1 | L58: 0 | M58: 0 | N58: 0 | O58: January
A59: TXN00072 | B59: 45317.35 | C59: PL | D59: PLN | E59: Adyen | F59: Bank Transfer | G59: 1640.96 | H59: Failed | I59: Fraud Suspected | J59: 2.1 | K59: 0.2327 | L59: 0 | M59: 0 | N59: 0 | O59: January
A60: TXN00062 | B60: 45317.719 | C60: GB | D60: GBP | E60: Worldpay | F60: Debit Card | G60: 4009.07 | H60: Pending | J60: 2.5 | K60: 1.1802 | L60: 0 | M60: 0 | N60: 0 | O60: January
A61: TXN00445 | B61: 45317.979 | C61: IT | D61: EUR | E61: PaySafe | F61: Credit Card | G61: 1695.95 | H61: Success | J61: 3.2 | K61: 1 | L61: 54.27 | M61: 1641.68 | N61: 1695.95 | O61: January
A62: TXN00962 | B62: 45318.417 | C62: GB | D62: GBP | E62: Worldpay | F62: Bank Transfer | G62: 4244.6 | H62: Pending | J62: 2.5 | K62: 1.1802 | L62: 0 | M62: 0 | N62: 0 | O62: January
A63: TXN00928 | B63: 45318.458 | C63: ES | D63: EUR | E63: Worldpay | F63: E-Wallet | G63: 4983.73 | H63: Pending | J63: 2.5 | K63: 1 | L63: 0 | M63: 0 | N63: 0 | O63: January
A64: TXN00248 | B64: 45318.771 | C64: FR | D64: EUR | E64: Checkout.com | F64: Crypto | G64: 3875.28 | H64: Failed | I64: Card Declined | J64: 1.9 | K64: 1 | L64: 0 | M64: 0 | N64: 0 | O64: January
A65: TXN00934 | B65: 45319.256 | C65: DE | D65: EUR | E65: Adyen | F65: Debit Card | G65: 188.95 | H65: Success | J65: 2.1 | K65: 1 | L65: 3.97 | M65: 184.98 | N65: 188.95 | O65: January
A66: TXN00346 | B66: 45319.458 | C66: NL | D66: EUR | E66: Adyen | F66: Debit Card | G66: 4077.93 | H66: Pending | J66: 2.1 | K66: 1 | L66: 0 | M66: 0 | N66: 0 | O66: January
A67: TXN00167 | B67: 45320.009 | C67: IT | D67: EUR | E67: Adyen | F67: Debit Card | G67: 3823.16 | H67: Success | J67: 2.1 | K67: 1 | L67: 80.29 | M67: 3742.87 | N67: 3823.16 | O67: January
A68: TXN00903 | B68: 45320.097 | C68: NO | D68: NOK | E68: PaySafe | F68: Credit Card | G68: 4503.87 | H68: Failed | I68: Fraud Suspected | J68: 3.2 | K68: 0.086 | L68: 0 | M68: 0 | N68: 0 | O68: January
A69: TXN00414 | B69: 45320.318 | C69: ES | D69: EUR | E69: Stripe | F69: Crypto | G69: 2395.17 | H69: Success | J69: 2.9 | K69: 1 | L69: 69.46 | M69: 2325.71 | N69: 2395.17 | O69: January
A70: TXN00886 | B70: 45320.885 | C70: ES | D70: EUR | E70: Adyen | F70: E-Wallet | G70: 2966.73 | H70: Success | J70: 2.1 | K70: 1 | L70: 62.3 | M70: 2904.43 | N70: 2966.73 | O70: January
A71: TXN00942 | B71: 45320.961 | C71: SE | D71: SEK | E71: Checkout.com | F71: Bank Transfer | G71: 471.83 | H71: Success | J71: 1.9 | K71: 0.0874 | L71: 0.783104 | M71: 40.454838 | N71: 41.237942 | O71: January
A72: TXN00033 | B72: 45321.067 | C72: NL | D72: EUR | E72: Checkout.com | F72: Crypto | G72: 795.59 | H72: Pending | J72: 1.9 | K72: 1 | L72: 0 | M72: 0 | N72: 0 | O72: January
A73: TXN00020 | B73: 45321.331 | C73: NO | D73: NOK | E73: Stripe | F73: Credit Card | G73: 3662.22 | H73: Success | J73: 2.9 | K73: 0.086 | L73: 9.1332 | M73: 305.81772 | N73: 314.95092 | O73: January
A74: TXN00275 | B74: 45321.728 | C74: IT | D74: EUR | E74: Stripe | F74: Bank Transfer | G74: 1279.74 | H74: Success | J74: 2.9 | K74: 1 | L74: 37.11 | M74: 1242.63 | N74: 1279.74 | O74: January
A75: TXN00884 | B75: 45323.026 | C75: DE | D75: EUR | E75: Adyen | F75: E-Wallet | G75: 1750.9 | H75: Pending | J75: 2.1 | K75: 1 | L75: 0 | M75: 0 | N75: 0 | O75: February
A76: TXN00744 | B76: 45323.498 | C76: SE | D76: SEK | E76: Stripe | F76: Credit Card | G76: 3519.74 | H76: Success | J76: 2.9 | K76: 0.0874 | L76: 8.920918 | M76: 298.70436 | N76: 307.62528 | O76: February
A77: TXN00964 | B77: 45323.667 | C77: CY | D77: EUR | E77: Checkout.com | F77: E-Wallet | G77: 2770.75 | H77: Success | J77: 1.9 | K77: 1 | L77: 52.64 | M77: 2718.11 | N77: 2770.75 | O77: February
A78: TXN00757 | B78: 45323.854 | C78: NO | D78: NOK | E78: Adyen | F78: Crypto | G78: 267.58 | H78: Success | J78: 2.1 | K78: 0.086 | L78: 0.48332 | M78: 22.52856 | N78: 23.01188 | O78: February
A79: TXN00201 | B79: 45324.162 | C79: NL | D79: EUR | E79: Checkout.com | F79: Crypto | G79: 92.01 | H79: Pending | J79: 1.9 | K79: 1 | L79: 0 | M79: 0 | N79: 0 | O79: February
A80: TXN00790 | B80: 45324.269 | C80: PL | D80: PLN | E80: Worldpay | F80: E-Wallet | G80: 612.8 | H80: Pending | J80: 2.5 | K80: 0.2327 | L80: 0 | M80: 0 | N80: 0 | O80: February
... A84: TXN00336 | B84: 45326.376 | C84: GB | D84: GBP | E84: Stripe | F84: E-Wallet | G84: 3243.37 | H84: Success | J84: 2.9 | K84: 1.1802 | L84: 111.00961 | M84: 3716.8157 | N84: 3827.8253 | O84: February
A85: TXN00671 | B85: 45326.529 | C85: IT | D85: EUR | E85: PaySafe | F85: Credit Card | G85: 105.2 | H85: Failed | I85: Card Declined | J85: 3.2 | K85: 1 | L85: 0 | M85: 0 | N85: 0 | O85: February
A86: TXN00162 | B86: 45327.199 | C86: DE | D86: EUR | E86: Stripe | F86: Crypto | G86: 1083.51 | H86: Failed | I86: Technical Error | J86: 2.9 | K86: 1 | L86: 0 | M86: 0 | N86: 0 | O86: February
A87: TXN00114 | B87: 45327.367 | C87: CY | D87: EUR | E87: PaySafe | F87: Crypto | G87: 1343.19 | H87: Success | J87: 3.2 | K87: 1 | L87: 42.98 | M87: 1300.21 | N87: 1343.19 | O87: February
A88: TXN00787 | B88: 45328.074 | C88: FR | D88: EUR | E88: Worldpay | F88: Credit Card | G88: 2361.39 | H88: Pending | J88: 2.5 | K88: 1 | L88: 0 | M88: 0 | N88: 0 | O88: February
A89: TXN00606 | B89: 45328.09 | C89: PL | D89: PLN | E89: Adyen | F89: E-Wallet | G89: 1591.22 | H89: Success | J89: 2.1 | K89: 0.2327 | L89: 7.776834 | M89: 362.50006 | N89: 370.27689 | O89: February
A90: TXN00645 | B90: 45328.378 | C90: ES | D90: EUR | E90: Checkout.com | F90: Credit Card | G90: 515.11 | H90: Success | J90: 1.9 | K90: 1 | L90: 9.79 | M90: 505.32 | N90: 515.11 | O90: February
A91: TXN00169 | B91: 45328.538 | C91: DE | D91: EUR | E91: Worldpay | F91: Credit Card | G91: 2304.17 | H91: Success | J91: 2.5 | K91: 1 | L91: 57.6 | M91: 2246.57 | N91: 2304.17 | O91: February
A92: TXN00025 | B92: 45328.677 | C92: IT | D92: EUR | E92: Worldpay | F92: Debit Card | G92: 2700.78 | H92: Pending | J92: 2.5 | K92: 1 | L92: 0 | M92: 0 | N92: 0 | O92: February
A93: TXN00373 | B93: 45328.706 | C93: DE | D93: EUR | E93: PaySafe | F93: E-Wallet | G93: 668.59 | H93: Pending | J93: 3.2 | K93: 1 | L93: 0 | M93: 0 | N93: 0 | O93: February
A94: TXN00315 | B94: 45329.095 | C94: FR | D94: EUR | E94: Worldpay | F94: Debit Card | G94: 3700.88 | H94: Success | J94: 2.5 | K94: 1 | L94: 92.52 | M94: 3608.36 | N94: 3700.88 | O94: February
A95: TXN00224 | B95: 45329.181 | C95: GB | D95: GBP | E95: Worldpay | F95: Bank Transfer | G95: 3403.74 | H95: Success | J95: 2.5 | K95: 1.1802 | L95: 100.42322 | M95: 3916.6707 | N95: 4017.0939 | O95: February
A96: TXN00291 | B96: 45329.285 | C96: NO | D96: NOK | E96: Checkout.com | F96: Debit Card | G96: 2402.18 | H96: Success | J96: 1.9 | K96: 0.086 | L96: 3.92504 | M96: 202.66244 | N96: 206.58748 | O96: February
A97: TXN00241 | B97: 45329.522 | C97: NL | D97: EUR | E97: Checkout.com | F97: E-Wallet | G97: 4128.3 | H97: Pending | J97: 1.9 | K97: 1 | L97: 0 | M97: 0 | N97: 0 | O97: February
A98: TXN00427 | B98: 45330.748 | C98: GB | D98: GBP | E98: PaySafe | F98: Crypto | G98: 4926.53 | H98: Failed | I98: Insufficient Funds | J98: 3.2 | K98: 1.1802 | L98: 0 | M98: 0 | N98: 0 | O98: February
A99: TXN00357 | B99: 45330.868 | C99: GB | D99: GBP | E99: Worldpay | F99: Crypto | G99: 3751.51 | H99: Success | J99: 2.5 | K99: 1.1802 | L99: 110.69096 | M99: 4316.8411 | N99: 4427.5321 | O99: February
A100: TXN00300 | B100: 45330.877 | C100: DE | D100: EUR | E100: Worldpay | F100: Debit Card | G100: 4214.3 | H100: Success | J100: 2.5 | K100: 1 | L100: 105.36 | M100: 4108.94 | N100: 4214.3 | O100: February
A101: TXN00188 | B101: 45331.412 | C101: GB | D101: GBP | E101: Checkout.com | F101: Crypto | G101: 4177.25 | H101: Pending | J101: 1.9 | K101: 1.1802 | L101: 0 | M101: 0 | N101: 0 | O101: February
A102: TXN00386 | B102: 45331.766 | C102: GB | D102: GBP | E102: Checkout.com | F102: Credit Card | G102: 904.93 | H102: Pending | J102: 1.9 | K102: 1.1802 | L102: 0 | M102: 0 | N102: 0 | O102: February
A103: TXN00894 | B103: 45331.869 | C103: IT | D103: EUR | E103: Checkout.com | F103: E-Wallet | G103: 2170.22 | H103: Pending | J103: 1.9 | K103: 1 | L103: 0 | M103: 0 | N103: 0 | O103: February
...

Sheet Tasks
B2: Task 1 — Conversion Rate by PSP Provider
B4: n/n | C4: PSP Provider | D4: Success Transactions | E4: Overall Transactions | F4: Success Rate (%)
B5: 1 | C5: {=_xlfn.UNIQUE('Raw_Data_Combined'!$E$2:$E$1001)} -> Worldpay | D5: =COUNTIFS(Raw_Data_Combined[PSP Provider],$C5,Raw_Data_Combined[Status],"Success") -> 105 | E5: =COUNTIF(Raw_Data_Combined[PSP Provider],Tasks!$C5) -> 194 | F5: =D5/E5 -> 0.54123711
B6: 2 | C6: Stripe | D6: =COUNTIFS(Raw_Data_Combined[PSP Provider],$C6,Raw_Data_Combined[Status],"Success") -> 101 | E6: =COUNTIF(Raw_Data_Combined[PSP Provider],Tasks!$C6) -> 186 | F6: =D6/E6 -> 0.54301075
B7: 3 | C7: Checkout.com | D7: =COUNTIFS(Raw_Data_Combined[PSP Provider],$C7,Raw_Data_Combined[Status],"Success") -> 130 | E7: =COUNTIF(Raw_Data_Combined[PSP Provider],Tasks!$C7) -> 221 | F7: =D7/E7 -> 0.58823529
B8: 4 | C8: PaySafe | D8: =COUNTIFS(Raw_Data_Combined[PSP Provider],$C8,Raw_Data_Combined[Status],"Success") -> 120 | E8: =COUNTIF(Raw_Data_Combined[PSP Provider],Tasks!$C8) -> 210 | F8: =D8/E8 -> 0.57142857
B9: 5 | C9: Adyen | D9: =COUNTIFS(Raw_Data_Combined[PSP Provider],$C9,Raw_Data_Combined[Status],"Success") -> 98 | E9: =COUNTIF(Raw_Data_Combined[PSP Provider],Tasks!$C9) -> 189 | F9: =D9/E9 -> 0.51851852
B13: Task 2 — Revenue & Fee Analysis by Provider
B15: n/n | C15: PSP Provider | D15: Net Amount (€) | E15: Fee Amount (€) | F15: Overall Transactions
B16: 1 | C16: {=_xlfn.UNIQUE('Raw_Data_Combined'!$E$2:$E$1001)} -> Worldpay | D16: =SUMIFS(Raw_Data_Combined[Net Amount EUR],Raw_Data_Combined[PSP Provider],$C16) -> 173586.54 | E16: =SUMIFS(Raw_Data_Combined[Fee Amount EUR],Raw_Data_Combined[PSP Provider],$C16) -> 4450.9076 | F16: =_xlfn.XLOOKUP($C16,$C$5:$C$9,$E$5:$E$9) -> 194
B17: 2 | C17: Stripe | D17: =SUMIFS(Raw_Data_Combined[Net Amount EUR],Raw_Data_Combined[PSP Provider],$C17) -> 192606.49 | E17: =SUMIFS(Raw_Data_Combined[Fee Amount EUR],Raw_Data_Combined[PSP Provider],$C17) -> 5752.3726 | F17: =_xlfn.XLOOKUP($C17,$C$5:$C$9,$E$5:$E$9) -> 186
B18: 3 | C18: Checkout.com | D18: =SUMIFS(Raw_Data_Combined[Net Amount EUR],Raw_Data_Combined[PSP Provider],$C18) -> 249324.19 | E18: =SUMIFS(Raw_Data_Combined[Fee Amount EUR],Raw_Data_Combined[PSP Provider],$C18) -> 4828.8748 | F18: =_xlfn.XLOOKUP($C18,$C$5:$C$9,$E$5:$E$9) -> 221
B19: 4 | C19: PaySafe | D19: =SUMIFS(Raw_Data_Combined[Net Amount EUR],Raw_Data_Combined[PSP Provider],$C19) -> 215751.9 | E19: =SUMIFS(Raw_Data_Combined[Fee Amount EUR],Raw_Data_Combined[PSP Provider],$C19) -> 7132.3015 | F19: =_xlfn.XLOOKUP($C19,$C$5:$C$9,$E$5:$E$9) -> 210
B20: 5 | C20: Adyen | D20: =SUMIFS(Raw_Data_Combined[Net Amount EUR],Raw_Data_Combined[PSP Provider],$C20) -> 193122.18 | E20: =SUMIFS(Raw_Data_Combined[Fee Amount EUR],Raw_Data_Combined[PSP Provider],$C20) -> 4142.5884 | F20: =_xlfn.XLOOKUP($C20,$C$5:$C$9,$E$5:$E$9) -> 189
B24: Task 3 — Performance by GEO
B26: n/n | C26: GEO | D26: Overall Transactions | E26: Success Rate (%) | F26: Avg Transaction Amount (All Statuses, €) | G26: Success Average Transaction Amount (€) | H26: Net Revenue (€)
B27: 1 | C27: {=_xlfn.UNIQUE('Raw_Data_Combined'!$C$2:$C$1001)} -> SE | D27: =COUNTIF(Raw_Data_Combined[GEO],$C27) -> 100 | E27: =COUNTIFS(Raw_Data_Combined[GEO],$C27,Raw_Data_Combined[Status],"Success")/$D27 -> 0.49 | F27: =AVERAGEIF(Raw_Data_Combined[GEO],Tasks!C27,Raw_Data_Combined[Gross Amount EUR]) -> 94.825766 | G27: =AVERAGEIFS(Raw_Data_Combined[Gross Amount EUR],Raw_Data_Combined[GEO],Tasks!$C27,Raw_Data_Combined[Status],"Success") -> 193.52197 | H27: =SUMIFS(Raw_Data_Combined[Net Amount EUR],Raw_Data_Combined[GEO],$C27) -> 9240.6298
B28: 2 | C28: NO | D28: =COUNTIF(Raw_Data_Combined[GEO],$C28) -> 98 | E28: =COUNTIFS(Raw_Data_Combined[GEO],$C28,Raw_Data_Combined[Status],"Success")/$D28 -> 0.58163265 | F28: =AVERAGEIF(Raw_Data_Combined[GEO],Tasks!C28,Raw_Data_Combined[Gross Amount EUR]) -> 116.35897 | G28: =AVERAGEIFS(Raw_Data_Combined[Gross Amount EUR],Raw_Data_Combined[GEO],Tasks!$C28,Raw_Data_Combined[Status],"Success") -> 200.05576 | H28: =SUMIFS(Raw_Data_Combined[Net Amount EUR],Raw_Data_Combined[GEO],$C28) -> 11128.355
B29: 3 | C29: ES | D29: =COUNTIF(Raw_Data_Combined[GEO],$C29) -> 80 | E29: =COUNTIFS(Raw_Data_Combined[GEO],$C29,Raw_Data_Combined[Status],"Success")/$D29 -> 0.5125 | F29: =AVERAGEIF(Raw_Data_Combined[GEO],Tasks!C29,Raw_Data_Combined[Gross Amount EUR]) -> 1418.3263 | G29: =AVERAGEIFS(Raw_Data_Combined[Gross Amount EUR],Raw_Data_Combined[GEO],Tasks!$C29,Raw_Data_Combined[Status],"Success") -> 2767.4659 | H29: =SUMIFS(Raw_Data_Combined[Net Amount EUR],Raw_Data_Combined[GEO],$C29) -> 110471.49
B30: 4 | C30: FR | D30: =COUNTIF(Raw_Data_Combined[GEO],$C30) -> 101 | E30: =COUNTIFS(Raw_Data_Combined[GEO],$C30,Raw_Data_Combined[Status],"Success")/$D30 -> 0.63366337 | F30: =AVERAGEIF(Raw_Data_Combined[GEO],Tasks!C30,Raw_Data_Combined[Gross Amount EUR]) -> 1773.3712 | G30: =AVERAGEIFS(Raw_Data_Combined[Gross Amount EUR],Raw_Data_Combined[GEO],Tasks!$C30,Raw_Data_Combined[Status],"Success") -> 2798.6014 | H30: =SUMIFS(Raw_Data_Combined[Net Amount EUR],Raw_Data_Combined[GEO],$C30) -> 174641.67
B31: 5 | C31: GB | D31: =COUNTIF(Raw_Data_Combined[GEO],$C31) -> 113 | E31: =COUNTIFS(Raw_Data_Combined[GEO],$C31,Raw_Data_Combined[Status],"Success")/$D31 -> 0.51327434 | F31: =AVERAGEIF(Raw_Data_Combined[GEO],Tasks!C31,Raw_Data_Combined[Gross Amount EUR]) -> 1467.2815 | G31: =AVERAGEIFS(Raw_Data_Combined[Gross Amount EUR],Raw_Data_Combined[GEO],Tasks!$C31,Raw_Data_Combined[Status],"Success") -> 2858.669 | H31: =SUMIFS(Raw_Data_Combined[Net Amount EUR],Raw_Data_Combined[GEO],$C31) -> 161735.55
B32: 6 | C32: PL | D32: =COUNTIF(Raw_Data_Combined[GEO],$C32) -> 97 | E32: =COUNTIFS(Raw_Data_Combined[GEO],$C32,Raw_Data_Combined[Status],"Success")/$D32 -> 0.57731959 | F32: =AVERAGEIF(Raw_Data_Combined[GEO],Tasks!C32,Raw_Data_Combined[Gross Amount EUR]) -> 373.92335 | G32: =AVERAGEIFS(Raw_Data_Combined[Gross Amount EUR],Raw_Data_Combined[GEO],Tasks!$C32,Raw_Data_Combined[Status],"Success") -> 647.68866 | H32: =SUMIFS(Raw_Data_Combined[Net Amount EUR],Raw_Data_Combined[GEO],$C32) -> 35308.793
B33: 7 | C33: NL | D33: =COUNTIF(Raw_Data_Combined[GEO],$C33) -> 125 | E33: =COUNTIFS(Raw_Data_Combined[GEO],$C33,Raw_Data_Combined[Status],"Success")/$D33 -> 0.56 | F33: =AVERAGEIF(Raw_Data_Combined[GEO],Tasks!C33,Raw_Data_Combined[Gross Amount EUR]) -> 1287.8441 | G33: =AVERAGEIFS(Raw_Data_Combined[Gross Amount EUR],Raw_Data_Combined[GEO],Tasks!$C33,Raw_Data_Combined[Status],"Success") -> 2299.7216 | H33: =SUMIFS(Raw_Data_Combined[Net Amount EUR],Raw_Data_Combined[GEO],$C33) -> 157032.23
B34: 8 | C34: IT | D34: =COUNTIF(Raw_Data_Combined[GEO],$C34) -> 91 | E34: =COUNTIFS(Raw_Data_Combined[GEO],$C34,Raw_Data_Combined[Status],"Success")/$D34 -> 0.6043956 | F34: =AVERAGEIF(Raw_Data_Combined[GEO],Tasks!C34,Raw_Data_Combined[Gross Amount EUR]) -> 1358.9085 | G34: =AVERAGEIFS(Raw_Data_Combined[Gross Amount EUR],Raw_Data_Combined[GEO],Tasks!$C34,Raw_Data_Combined[Status],"Success") -> 2248.3758 | H34: =SUMIFS(Raw_Data_Combined[Net Amount EUR],Raw_Data_Combined[GEO],$C34) -> 120668.87
B35: 9 | C35: CY | D35: =COUNTIF(Raw_Data_Combined[GEO],$C35) -> 108 | E35: =COUNTIFS(Raw_Data_Combined[GEO],$C35,Raw_Data_Combined[Status],"Success")/$D35 -> 0.56481481 | F35: =AVERAGEIF(Raw_Data_Combined[GEO],Tasks!C35,Raw_Data_Combined[Gross Amount EUR]) -> 1416.9217 | G35: =AVERAGEIFS(Raw_Data_Combined[Gross Amount EUR],Raw_Data_Combined[GEO],Tasks!$C35,Raw_Data_Combined[Status],"Success") -> 2508.6482 | H35: =SUMIFS(Raw_Data_Combined[Net Amount EUR],Raw_Data_Combined[GEO],$C35) -> 149085.7
B36: 10 | C36: DE | D36: =COUNTIF(Raw_Data_Combined[GEO],$C36) -> 87 | E36: =COUNTIFS(Raw_Data_Combined[GEO],$C36,Raw_Data_Combined[Status],"Success")/$D36 -> 0.49425287 | F36: =AVERAGEIF(Raw_Data_Combined[GEO],Tasks!C36,Raw_Data_Combined[Gross Amount EUR]) -> 1120.6195 | G36: =AVERAGEIFS(Raw_Data_Combined[Gross Amount EUR],Raw_Data_Combined[GEO],Tasks!$C36,Raw_Data_Combined[Status],"Success") -> 2267.3 | H36: =SUMIFS(Raw_Data_Combined[Net Amount EUR],Raw_Data_Combined[GEO],$C36) -> 95078
B40: Task 4 — Decline Reason Analysis
B42: n/n | C42: Decline Reason | D42: Count | E42: Percentage of Total
B43: 1 | C43: {=_xlfn.UNIQUE(_xlfn._xlws.FILTER(Raw_Data_Combined[Decline Reason], Raw_Data_Combined[Decline Reason]<>""))} -> Card Declined | D43: =COUNTIF(Raw_Data_Combined[Decline Reason],$C43) -> 49 | E43: =$D43/SUM($D$43:$D$47) -> 0.22477064
B44: 2 | C44: Technical Error | D44: =COUNTIF(Raw_Data_Combined[Decline Reason],$C44) -> 44 | E44: =$D44/SUM($D$43:$D$47) -> 0.20183486
B45: 3 | C45: Fraud Suspected | D45: =COUNTIF(Raw_Data_Combined[Decline Reason],$C45) -> 51 | E45: =$D45/SUM($D$43:$D$47) -> 0.23394495
B46: 4 | C46: Insufficient Funds | D46: =COUNTIF(Raw_Data_Combined[Decline Reason],$C46) -> 33 | E46: =$D46/SUM($D$43:$D$47) -> 0.15137615
B47: 5 | C47: Expired Card | D47: =COUNTIF(Raw_Data_Combined[Decline Reason],$C47) -> 41 | E47: =$D47/SUM($D$43:$D$47) -> 0.18807339
B51: Task 5 — Best PSP Provider per GEO (Top 3)
B53: TOP GEO
B54: n/n | C54: TOP GEO
B55: 1 | C55: {=_xlfn.TAKE(_xlfn._xlws.SORT(C27:D36,2,-1),3,1)} -> NL
B56: 2 | C56: GB
B57: 3 | C57: CY
B59: Successful Transaction Rate Per Provider Per GEO
B60: n/n | C60: PSP Provider | D60: =C55 -> NL | E60: =C56 -> GB | F60: =C57 -> CY
B61: 1 | C61: {=_xlfn.UNIQUE('Raw_Data_Combined'!$E$2:$E$1001)} -> Worldpay | D61: =COUNTIFS(Raw_Data_Combined[GEO],D$60,Raw_Data_Combined[Status],"Success",Raw_Data_Combined[PSP Provider],Tasks!$C16)/COUNTIFS(Raw_Data_Combined[GEO],D$60,Raw_Data_Combined[PSP Provider],Tasks!$C16) -> 0.44444444 | E61: =COUNTIFS(Raw_Data_Combined[GEO],E$60,Raw_Data_Combined[Status],"Success",Raw_Data_Combined[PSP Provider],Tasks!$C16)/COUNTIFS(Raw_Data_Combined[GEO],E$60,Raw_Data_Combined[PSP Provider],Tasks!$C16) -> 0.5 | F61: =COUNTIFS(Raw_Data_Combined[GEO],F$60,Raw_Data_Combined[Status],"Success",Raw_Data_Combined[PSP Provider],Tasks!$C16)/COUNTIFS(Raw_Data_Combined[GEO],F$60,Raw_Data_Combined[PSP Provider],Tasks!$C16) -> 0.47058824
B62: 2 | C62: Stripe | D62: =COUNTIFS(Raw_Data_Combined[GEO],D$60,Raw_Data_Combined[Status],"Success",Raw_Data_Combined[PSP Provider],Tasks!$C17)/COUNTIFS(Raw_Data_Combined[GEO],D$60,Raw_Data_Combined[PSP Provider],Tasks!$C17) -> 0.53571429 | E62: =COUNTIFS(Raw_Data_Combined[GEO],E$60,Raw_Data_Combined[Status],"Success",Raw_Data_Combined[PSP Provider],Tasks!$C17)/COUNTIFS(Raw_Data_Combined[GEO],E$60,Raw_Data_Combined[PSP Provider],Tasks!$C17) -> 0.47368421 | F62: =COUNTIFS(Raw_Data_Combined[GEO],F$60,Raw_Data_Combined[Status],"Success",Raw_Data_Combined[PSP Provider],Tasks!$C17)/COUNTIFS(Raw_Data_Combined[GEO],F$60,Raw_Data_Combined[PSP Provider],Tasks!$C17) -> 0.57692308
B63: 3 | C63: Checkout.com | D63: =COUNTIFS(Raw_Data_Combined[GEO],D$60,Raw_Data_Combined[Status],"Success",Raw_Data_Combined[PSP Provider],Tasks!$C18)/COUNTIFS(Raw_Data_Combined[GEO],D$60,Raw_Data_Combined[PSP Provider],Tasks!$C18) -> 0.54545455 | E63: =COUNTIFS(Raw_Data_Combined[GEO],E$60,Raw_Data_Combined[Status],"Success",Raw_Data_Combined[PSP Provider],Tasks!$C18)/COUNTIFS(Raw_Data_Combined[GEO],E$60,Raw_Data_Combined[PSP Provider],Tasks!$C18) -> 0.65384615 | F63: =COUNTIFS(Raw_Data_Combined[GEO],F$60,Raw_Data_Combined[Status],"Success",Raw_Data_Combined[PSP Provider],Tasks!$C18)/COUNTIFS(Raw_Data_Combined[GEO],F$60,Raw_Data_Combined[PSP Provider],Tasks!$C18) -> 0.57142857
B64: 4 | C64: PaySafe | D64: =COUNTIFS(Raw_Data_Combined[GEO],D$60,Raw_Data_Combined[Status],"Success",Raw_Data_Combined[PSP Provider],Tasks!$C19)/COUNTIFS(Raw_Data_Combined[GEO],D$60,Raw_Data_Combined[PSP Provider],Tasks!$C19) -> 0.62962963 | E64: =COUNTIFS(Raw_Data_Combined[GEO],E$60,Raw_Data_Combined[Status],"Success",Raw_Data_Combined[PSP Provider],Tasks!$C19)/COUNTIFS(Raw_Data_Combined[GEO],E$60,Raw_Data_Combined[PSP Provider],Tasks!$C19) -> 0.43478261 | F64: =COUNTIFS(Raw_Data_Combined[GEO],F$60,Raw_Data_Combined[Status],"Success",Raw_Data_Combined[PSP Provider],Tasks!$C19)/COUNTIFS(Raw_Data_Combined[GEO],F$60,Raw_Data_Combined[PSP Provider],Tasks!$C19) -> 0.7
B65: 5 | C65: Adyen | D65: =COUNTIFS(Raw_Data_Combined[GEO],D$60,Raw_Data_Combined[Status],"Success",Raw_Data_Combined[PSP Provider],Tasks!$C20)/COUNTIFS(Raw_Data_Combined[GEO],D$60,Raw_Data_Combined[PSP Provider],Tasks!$C20) -> 0.63157895 | E65: =COUNTIFS(Raw_Data_Combined[GEO],E$60,Raw_Data_Combined[Status],"Success",Raw_Data_Combined[PSP Provider],Tasks!$C20)/COUNTIFS(Raw_Data_Combined[GEO],E$60,Raw_Data_Combined[PSP Provider],Tasks!$C20) -> 0.47368421 | F65: =COUNTIFS(Raw_Data_Combined[GEO],F$60,Raw_Data_Combined[Status],"Success",Raw_Data_Combined[PSP Provider],Tasks!$C20)/COUNTIFS(Raw_Data_Combined[GEO],F$60,Raw_Data_Combined[PSP Provider],Tasks!$C20) -> 0.5
B67: Best PSP Provider per GEO
B68: n/n | C68: TOP GEO | D68: Best Provider
B69: 1 | C69: {=_xlfn.TAKE(_xlfn._xlws.SORT(C27:D36,2,-1),3,1)} -> NL | D69: =INDEX($C$61:$C$65, MATCH(MAX($D$61:$D$65), $D$61:$D$65, 0)) -> Adyen
B70: 2 | C70: GB | D70: =INDEX($C$61:$C$65, MATCH(MAX($E$61:$E$65), $E$61:$E$65, 0)) -> Checkout.com
B71: 3 | C71: CY | D71: =INDEX($C$61:$C$65, MATCH(MAX($F$61:$F$65), $F$61:$F$65, 0)) -> PaySafe
B74: Task 6 — Pending Transaction Analysis
B76: n/n | C76: PSP Provider | D76: Pending Count | E76: Total Transactions | F76: Pending Rate (%)
B77: 1 | C77: =$C$5 -> Worldpay | D77: =COUNTIFS(Raw_Data_Combined[PSP Provider],C77,Raw_Data_Combined[Status],"Pending") -> 48 | E77: =$E$5 -> 194 | F77: =D77/E77 -> 0.24742268
B78: 2 | C78: =$C$6 -> Stripe | D78: =COUNTIFS(Raw_Data_Combined[PSP Provider],C78,Raw_Data_Combined[Status],"Pending") -> 45 | E78: =$E$6 -> 186 | F78: =D78/E78 -> 0.24193548
B79: 3 | C79: =$C$7 -> Checkout.com | D79: =COUNTIFS(Raw_Data_Combined[PSP Provider],C79,Raw_Data_Combined[Status],"Pending") -> 46 | E79: =$E$7 -> 221 | F79: =D79/E79 -> 0.2081448
B80: 4 | C80: =$C$8 -> PaySafe | D80: =COUNTIFS(Raw_Data_Combined[PSP Provider],C80,Raw_Data_Combined[Status],"Pending") -> 47 | E80: =$E$8 -> 210 | F80: =D80/E80 -> 0.22380952
B81: 5 | C81: =$C$9 -> Adyen | D81: =COUNTIFS(Raw_Data_Combined[PSP Provider],C81,Raw_Data_Combined[Status],"Pending") -> 42 | E81: =$E$9 -> 189 | F81: =D81/E81 -> 0.22222222
B84: Pending Transactions by GEO
B85: n/n | C85: GEO | D85: Pending Count | E85: Total Transactions | F85: Pending Rate (%)
B86: 1 | C86: =$C$27 -> SE | D86: =COUNTIFS(Raw_Data_Combined[GEO],C86,Raw_Data_Combined[Status],"Pending") -> 20 | E86: =$D$27 -> 100 | F86: =D86/E86 -> 0.2
B87: 2 | C87: =$C$28 -> NO | D87: =COUNTIFS(Raw_Data_Combined[GEO],C87,Raw_Data_Combined[Status],"Pending") -> 22 | E87: =$D$28 -> 98 | F87: =D87/E87 -> 0.2244898
B88: 3 | C88: =$C$29 -> ES | D88: =COUNTIFS(Raw_Data_Combined[GEO],C88,Raw_Data_Combined[Status],"Pending") -> 19 | E88: =$D$29 -> 80 | F88: =D88/E88 -> 0.2375
B89: 4 | C89: =$C$30 -> FR | D89: =COUNTIFS(Raw_Data_Combined[GEO],C89,Raw_Data_Combined[Status],"Pending") -> 22 | E89: =$D$30 -> 101 | F89: =D89/E89 -> 0.21782178
B90: 5 | C90: =$C$31 -> GB | D90: =COUNTIFS(Raw_Data_Combined[GEO],C90,Raw_Data_Combined[Status],"Pending") -> 28 | E90: =$D$31 -> 113 | F90: =D90/E90 -> 0.24778761
B91: 6 | C91: =$C$32 -> PL | D91: =COUNTIFS(Raw_Data_Combined[GEO],C91,Raw_Data_Combined[Status],"Pending") -> 23 | E91: =$D$32 -> 97 | F91: =D91/E91 -> 0.2371134
B92: 7 | C92: =$C$33 -> NL | D92: =COUNTIFS(Raw_Data_Combined[GEO],C92,Raw_Data_Combined[Status],"Pending") -> 26 | E92: =$D$33 -> 125 | F92: =D92/E92 -> 0.208
B93: 8 | C93: =$C$34 -> IT | D93: =COUNTIFS(Raw_Data_Combined[GEO],C93,Raw_Data_Combined[Status],"Pending") -> 22 | E93: =$D$34 -> 91 | F93: =D93/E93 -> 0.24175824
B94: 9 | C94: =$C$35 -> CY | D94: =COUNTIFS(Raw_Data_Combined[GEO],C94,Raw_Data_Combined[Status],"Pending") -> 25 | E94: =$D$35 -> 108 | F94: =D94/E94 -> 0.23148148
B95: 10 | C95: =$C$36 -> DE | D95: =COUNTIFS(Raw_Data_Combined[GEO],C95,Raw_Data_Combined[Status],"Pending") -> 21 | E95: =$D$36 -> 87 | F95: =D95/E95 -> 0.24137931
B97: Pending Transactions by Payment Method
B98: n/n | C98: Payment Method | D98: Pending Count | E98: Total Transactions | F98: Pending Rate (%)
B99: 1 | C99: Bank Transfer | D99: =COUNTIFS(Raw_Data_Combined[Payment Method],C99,Raw_Data_Combined[Status],"Pending") -> 51 | E99: =COUNTIF(Raw_Data_Combined[Payment Method],C99) -> 200 | F99: =D99/E99 -> 0.255
B100: 2 | C100: Credit Card | D100: =COUNTIFS(Raw_Data_Combined[Payment Method],C100,Raw_Data_Combined[Status],"Pending") -> 38 | E100: =COUNTIF(Raw_Data_Combined[Payment Method],C100) -> 179 | F100: =D100/E100 -> 0.2122905
B101: 3 | C101: Crypto | D101: =COUNTIFS(Raw_Data_Combined[Payment Method],C101,Raw_Data_Combined[Status],"Pending") -> 46 | E101: =COUNTIF(Raw_Data_Combined[Payment Method],C101) -> 196 | F101: =D101/E101 -> 0.23469388
B102: 4 | C102: Debit Card | D102: =COUNTIFS(Raw_Data_Combined[Payment Method],C102,Raw_Data_Combined[Status],"Pending") -> 49 | E102: =COUNTIF(Raw_Data_Combined[Payment Method],C102) -> 224 | F102: =D102/E102 -> 0.21875
B103: 5 | C103: E-Wallet | D103: =COUNTIFS(Raw_Data_Combined[Payment Method],C103,Raw_Data_Combined[Status],"Pending") -> 44 | E103: =COUNTIF(Raw_Data_Combined[Payment Method],C103) -> 201 | F103: =D103/E103 -> 0.21890547

Sheet Dashboards
B2: 📊 | C2: PSP Transaction Dashboard · 2024
B4: TOTAL TRANSACTIONS | D4: SUCCESS RATE | F4: TOTAL NET REVENUE | H4: AVG NET (ALL TXN) | J4: AVG SUCCESSFUL TRANSACTION
B5: =COUNTA(Raw_Data_Combined[Transaction ID]) -> 1000 | D5: =COUNTIF(Raw_Data_Combined[Status],"Success")/B5 -> 0.554 | F5: =SUM(Raw_Data_Combined[Net Amount EUR]) -> 1024391.3 | H5: =AVERAGE(Raw_Data_Combined[Net Amount EUR]) -> 1024.3913 | J5: =AVERAGEIFS(Raw_Data_Combined[Net Amount EUR],Raw_Data_Combined[Status],"Success") -> 1849.0818
B6: across all providers | D6: 554 of 1,000 successful | F6: after fees deducted | H6: per transaction incl non-success (net) | J6: per successful transaction (net)
B8: Transaction Status Breakdown | G8: Decline Reason Analysis
B9: Status | C9: Count | D9: % of Total | E9: Bar | G9: Decline Reason | H9: Count | I9: % of Declines | J9: Severity
B10: ✓ Success | C10: =COUNTIF(Raw_Data_Combined[Status],"Success") -> 554 | D10: =C10/SUM($C$10:$C$12) -> 0.554 | E10: =REPT("█",ROUND(D10*30,0)) -> █████████████████ | G10: {=_xlfn.TAKE(_xlfn._xlws.SORT(Tasks!C43:E47,3,-1),,1)} -> Fraud Suspected | H10: =VLOOKUP(G10,Tasks!$C$43:$E$47,2,FALSE) -> 51 | I10: =H10/SUM($H$10:$H$14) -> 0.23394495 | J10: 🔴 High
B11: ⏳ Pending | C11: =COUNTIF(Raw_Data_Combined[Status],"Pending") -> 228 | D11: =C11/SUM($C$10:$C$12) -> 0.228 | E11: =REPT("█",ROUND(D11*30,0)) -> ███████ | G11: Card Declined | H11: =VLOOKUP(G11,Tasks!$C$43:$E$47,2,FALSE) -> 49 | I11: =H11/SUM($H$10:$H$14) -> 0.22477064 | J11: 🟠 Medium
B12: ✗ Failed | C12: =COUNTIF(Raw_Data_Combined[Status],"Failed") -> 218 | D12: =C12/SUM($C$10:$C$12) -> 0.218 | E12: =REPT("█",ROUND(D12*30,0)) -> ███████ | G12: Technical Error | H12: =VLOOKUP(G12,Tasks!$C$43:$E$47,2,FALSE) -> 44 | I12: =H12/SUM($H$10:$H$14) -> 0.20183486 | J12: 🟠 Medium
G13: Expired Card | H13: =VLOOKUP(G13,Tasks!$C$43:$E$47,2,FALSE) -> 41 | I13: =H13/SUM($H$10:$H$14) -> 0.18807339 | J13: 🟡 Low
G14: Insufficient Funds | H14: =VLOOKUP(G14,Tasks!$C$43:$E$47,2,FALSE) -> 33 | I14: =H14/SUM($H$10:$H$14) -> 0.15137615 | J14: 🟡 Low
B15: PSP Provider Performance
B16: Provider | C16: Transactions | D16: Success Rate | E16: Net Revenue | F16: Fees Paid | G16: Fee % | H16: Avg Txn Value | I16: Avg Successful Txn Value
B17: {=_xlfn.TAKE(_xlfn._xlws.SORT(Tasks!C5:E9,3,-1),,1)} -> Checkout.com | C17: =VLOOKUP(Dashboards!B17,Tasks!$C$16:$F$20,4,FALSE) -> 221 | D17: =VLOOKUP(Dashboards!B17,Tasks!$C$5:$F$9,4,FALSE) -> 0.58823529 | E17: =VLOOKUP(Dashboards!B17,Tasks!$C$16:$E$20,2,FALSE) -> 249324.19 | F17: =VLOOKUP(Dashboards!B17,Tasks!$C$16:$E$20,3,FALSE) -> 4828.8748 | G17: =F17/(E17+F17) -> 0.018999868 | H17: =E17/C17 -> 1128.1638 | I17: =AVERAGEIFS(Raw_Data_Combined[Net Amount EUR],Raw_Data_Combined[PSP Provider],$B17,Raw_Data_Combined[Status],"Success") -> 1917.8784
B18: PaySafe | C18: =VLOOKUP(Dashboards!B18,Tasks!$C$16:$F$20,4,FALSE) -> 210 | D18: =VLOOKUP(Dashboards!B18,Tasks!$C$5:$F$9,4,FALSE) -> 0.57142857 | E18: =VLOOKUP(B18,Tasks!$C$16:$E$20,2,FALSE) -> 215751.9 | F18: =VLOOKUP(Dashboards!B18,Tasks!$C$16:$E$20,3,FALSE) -> 7132.3015 | G18: =F18/(E18+F18) -> 0.032000032 | H18: =E18/C18 -> 1027.39 | I18: =AVERAGEIFS(Raw_Data_Combined[Net Amount EUR],Raw_Data_Combined[PSP Provider],$B18,Raw_Data_Combined[Status],"Success") -> 1797.9325
B19: Worldpay | C19: =VLOOKUP(Dashboards!B19,Tasks!$C$16:$F$20,4,FALSE) -> 194 | D19: =VLOOKUP(Dashboards!B19,Tasks!$C$5:$F$9,4,FALSE) -> 0.54123711 | E19: =VLOOKUP(B19,Tasks!$C$16:$E$20,2,FALSE) -> 173586.54 | F19: =VLOOKUP(Dashboards!B19,Tasks!$C$16:$E$20,3,FALSE) -> 4450.9076 | G19: =F19/(E19+F19) -> 0.02499984 | H19: =E19/C19 -> 894.77595 | I19: =AVERAGEIFS(Raw_Data_Combined[Net Amount EUR],Raw_Data_Combined[PSP Provider],$B19,Raw_Data_Combined[Status],"Success") -> 1653.2051
B20: Adyen | C20: =VLOOKUP(Dashboards!B20,Tasks!$C$16:$F$20,4,FALSE) -> 189 | D20: =VLOOKUP(Dashboards!B20,Tasks!$C$5:$F$9,4,FALSE) -> 0.51851852 | E20: =VLOOKUP(B20,Tasks!$C$16:$E$20,2,FALSE) -> 193122.18 | F20: =VLOOKUP(Dashboards!B20,Tasks!$C$16:$E$20,3,FALSE) -> 4142.5884 | G20: =F20/(E20+F20) -> 0.021000143 | H20: =E20/C20 -> 1021.8105 | I20: =AVERAGEIFS(Raw_Data_Combined[Net Amount EUR],Raw_Data_Combined[PSP Provider],$B20,Raw_Data_Combined[Status],"Success") -> 1970.6345
B21: Stripe | C21: =VLOOKUP(Dashboards!B21,Tasks!$C$16:$F$20,4,FALSE) -> 186 | D21: =VLOOKUP(Dashboards!B21,Tasks!$C$5:$F$9,4,FALSE) -> 0.54301075 | E21: =VLOOKUP(B21,Tasks!$C$16:$E$20,2,FALSE) -> 192606.49 | F21: =VLOOKUP(Dashboards!B21,Tasks!$C$16:$E$20,3,FALSE) -> 5752.3726 | G21: =F21/(E21+F21) -> 0.028999827 | H21: =E21/C21 -> 1035.5188 | I21: =AVERAGEIFS(Raw_Data_Combined[Net Amount EUR],Raw_Data_Combined[PSP Provider],$B21,Raw_Data_Combined[Status],"Success") -> 1906.9949
B22: TOTAL | C22: =SUM(C17:C21) -> 1000 | D22: =COUNTIF(Raw_Data_Combined[Status],"Success")/C22 -> 0.554 | E22: =SUM(E17:E21) -> 1024391.3 | F22: =SUM(F17:F21) -> 26307.045 | G22: =F22/(E22+F22) -> 0.025037676 | H22: =E22/C22 -> 1024.3913 | I22: =J5 -> 1849.0818
B25: Monthly Transaction Volume & Revenue
B26: Month | C26: Transactions | D26: Net Revenue | E26: Success Rate
B27: Jan | C27: =COUNTIFS(Raw_Data_Combined[Date & Time],">="&DATE(2024,1,1),Raw_Data_Combined[Date & Time],"<"&DATE(2024,2,1)) -> 73 | D27: =SUMIFS(Raw_Data_Combined[Net Amount EUR],Raw_Data_Combined[Date & Time],">="&DATE(2024,1,1),Raw_Data_Combined[Date & Time],"<"&DATE(2024,2,1)) -> 65638.729 | E27: =COUNTIFS(Raw_Data_Combined[Date & Time],">="&DATE(2024,1,1),Raw_Data_Combined[Date & Time],"<"&DATE(2024,2,1),Raw_Data_Combined[Status],"Success")/C27 -> 0.47945205
B28: Feb | C28: =COUNTIFS(Raw_Data_Combined[Date & Time],">="&DATE(2024,2,1),Raw_Data_Combined[Date & Time],"<"&DATE(2024,3,1)) -> 81 | D28: =SUMIFS(Raw_Data_Combined[Net Amount EUR],Raw_Data_Combined[Date & Time],">="&DATE(2024,2,1),Raw_Data_Combined[Date & Time],"<"&DATE(2024,3,1)) -> 102582.11 | E28: =COUNTIFS(Raw_Data_Combined[Date & Time],">="&DATE(2024,2,1),Raw_Data_Combined[Date & Time],"<"&DATE(2024,3,1),Raw_Data_Combined[Status],"Success")/C28 -> 0.54320988
B29: Mar | C29: =COUNTIFS(Raw_Data_Combined[Date & Time],">="&DATE(2024,3,1),Raw_Data_Combined[Date & Time],"<"&DATE(2024,4,1)) -> 101 | D29: =SUMIFS(Raw_Data_Combined[Net Amount EUR],Raw_Data_Combined[Date & Time],">="&DATE(2024,3,1),Raw_Data_Combined[Date & Time],"<"&DATE(2024,4,1)) -> 70701.008 | E29: =COUNTIFS(Raw_Data_Combined[Date & Time],">="&DATE(2024,3,1),Raw_Data_Combined[Date & Time],"<"&DATE(2024,4,1),Raw_Data_Combined[Status],"Success")/C29 -> 0.48514851
B30: Apr | C30: =COUNTIFS(Raw_Data_Combined[Date & Time],">="&DATE(2024,4,1),Raw_Data_Combined[Date & Time],"<"&DATE(2024,5,1)) -> 75 | D30: =SUMIFS(Raw_Data_Combined[Net Amount EUR],Raw_Data_Combined[Date & Time],">="&DATE(2024,4,1),Raw_Data_Combined[Date & Time],"<"&DATE(2024,5,1)) -> 59781.091 | E30: =COUNTIFS(Raw_Data_Combined[Date & Time],">="&DATE(2024,4,1),Raw_Data_Combined[Date & Time],"<"&DATE(2024,5,1),Raw_Data_Combined[Status],"Success")/C30 -> 0.57333333
B31: May | C31: =COUNTIFS(Raw_Data_Combined[Date & Time],">="&DATE(2024,5,1),Raw_Data_Combined[Date & Time],"<"&DATE(2024,6,1)) -> 84 | D31: =SUMIFS(Raw_Data_Combined[Net Amount EUR],Raw_Data_Combined[Date & Time],">="&DATE(2024,5,1),Raw_Data_Combined[Date & Time],"<"&DATE(2024,6,1)) -> 89803.644 | E31: =COUNTIFS(Raw_Data_Combined[Date & Time],">="&DATE(2024,5,1),Raw_Data_Combined[Date & Time],"<"&DATE(2024,6,1),Raw_Data_Combined[Status],"Success")/C31 -> 0.54761905
B32: Jun | C32: =COUNTIFS(Raw_Data_Combined[Date & Time],">="&DATE(2024,6,1),Raw_Data_Combined[Date & Time],"<"&DATE(2024,7,1)) -> 71 | D32: =SUMIFS(Raw_Data_Combined[Net Amount EUR],Raw_Data_Combined[Date & Time],">="&DATE(2024,6,1),Raw_Data_Combined[Date & Time],"<"&DATE(2024,7,1)) -> 79661.03 | E32: =COUNTIFS(Raw_Data_Combined[Date & Time],">="&DATE(2024,6,1),Raw_Data_Combined[Date & Time],"<"&DATE(2024,7,1),Raw_Data_Combined[Status],"Success")/C32 -> 0.56338028
B33: Jul | C33: =COUNTIFS(Raw_Data_Combined[Date & Time],">="&DATE(2024,7,1),Raw_Data_Combined[Date & Time],"<"&DATE(2024,8,1)) -> 72 | D33: =SUMIFS(Raw_Data_Combined[Net Amount EUR],Raw_Data_Combined[Date & Time],">="&DATE(2024,7,1),Raw_Data_Combined[Date & Time],"<"&DATE(2024,8,1)) -> 66839.333 | E33: =COUNTIFS(Raw_Data_Combined[Date & Time],">="&DATE(2024,7,1),Raw_Data_Combined[Date & Time],"<"&DATE(2024,8,1),Raw_Data_Combined[Status],"Success")/C33 -> 0.47222222
B34: Aug | C34: =COUNTIFS(Raw_Data_Combined[Date & Time],">="&DATE(2024,8,1),Raw_Data_Combined[Date & Time],"<"&DATE(2024,9,1)) -> 97 | D34: =SUMIFS(Raw_Data_Combined[Net Amount EUR],Raw_Data_Combined[Date & Time],">="&DATE(2024,8,1),Raw_Data_Combined[Date & Time],"<"&DATE(2024,9,1)) -> 99286.391 | E34: =COUNTIFS(Raw_Data_Combined[Date & Time],">="&DATE(2024,8,1),Raw_Data_Combined[Date & Time],"<"&DATE(2024,9,1),Raw_Data_Combined[Status],"Success")/C34 -> 0.62886598
B35: Sep | C35: =COUNTIFS(Raw_Data_Combined[Date & Time],">="&DATE(2024,9,1),Raw_Data_Combined[Date & Time],"<"&DATE(2024,10,1)) -> 74 | D35: =SUMIFS(Raw_Data_Combined[Net Amount EUR],Raw_Data_Combined[Date & Time],">="&DATE(2024,9,1),Raw_Data_Combined[Date & Time],"<"&DATE(2024,10,1)) -> 86237.383 | E35: =COUNTIFS(Raw_Data_Combined[Date & Time],">="&DATE(2024,9,1),Raw_Data_Combined[Date & Time],"<"&DATE(2024,10,1),Raw_Data_Combined[Status],"Success")/C35 -> 0.60810811
B36: Oct | C36: =COUNTIFS(Raw_Data_Combined[Date & Time],">="&DATE(2024,10,1),Raw_Data_Combined[Date & Time],"<"&DATE(2024,11,1)) -> 96 | D36: =SUMIFS(Raw_Data_Combined[Net Amount EUR],Raw_Data_Combined[Date & Time],">="&DATE(2024,10,1),Raw_Data_Combined[Date & Time],"<"&DATE(2024,11,1)) -> 122066.1 | E36: =COUNTIFS(Raw_Data_Combined[Date & Time],">="&DATE(2024,10,1),Raw_Data_Combined[Date & Time],"<"&DATE(2024,11,1),Raw_Data_Combined[Status],"Success")/C36 -> 0.61458333
B37: Nov | C37: =COUNTIFS(Raw_Data_Combined[Date & Time],">="&DATE(2024,11,1),Raw_Data_Combined[Date & Time],"<"&DATE(2024,12,1)) -> 76 | D37: =SUMIFS(Raw_Data_Combined[Net Amount EUR],Raw_Data_Combined[Date & Time],">="&DATE(2024,11,1),Raw_Data_Combined[Date & Time],"<"&DATE(2024,12,1)) -> 81808.609 | E37: =COUNTIFS(Raw_Data_Combined[Date & Time],">="&DATE(2024,11,1),Raw_Data_Combined[Date & Time],"<"&DATE(2024,12,1),Raw_Data_Combined[Status],"Success")/C37 -> 0.53947368
B38: Dec | C38: =COUNTIFS(Raw_Data_Combined[Date & Time],">="&DATE(2024,12,1),Raw_Data_Combined[Date & Time],"<"&DATE(2025,1,1)) -> 100 | D38: =SUMIFS(Raw_Data_Combined[Net Amount EUR],Raw_Data_Combined[Date & Time],">="&DATE(2024,12,1),Raw_Data_Combined[Date & Time],"<"&DATE(2025,1,1)) -> 99985.861 | E38: =COUNTIFS(Raw_Data_Combined[Date & Time],">="&DATE(2024,12,1),Raw_Data_Combined[Date & Time],"<"&DATE(2025,1,1),Raw_Data_Combined[Status],"Success")/C38 -> 0.57
B41: GEO Transaction Volume & Revenue | G41: Successful Transaction Rate Per Provider by GEO (TOP 3)
B42: GEO | C42: Transactions | D42: Net Revenue | E42: Success Rate | G42: PSP Provider | H42: Top 3 GEO
B43: {=_xlfn._xlws.SORT(Tasks!C27:D36,2,-1)} -> NL | C43: 125 | D43: =SUMIFS(Raw_Data_Combined[Net Amount EUR],Raw_Data_Combined[GEO], Dashboards!B43) -> 157032.23 | E43: =VLOOKUP(B43,Tasks!$C$27:$E$36,3,FALSE) -> 0.56 | H43: NL | I43: GB | J43: CY
B44: GB | C44: 113 | D44: =SUMIFS(Raw_Data_Combined[Net Amount EUR],Raw_Data_Combined[GEO], Dashboards!B44) -> 161735.55 | E44: =VLOOKUP(B44,Tasks!$C$27:$E$36,3,FALSE) -> 0.51327434 | G44: =Tasks!C61 -> Worldpay | H44: =Tasks!D61 -> 0.44444444 | I44: =Tasks!E61 -> 0.5 | J44: =Tasks!F61 -> 0.47058824
B45: CY | C45: 108 | D45: =SUMIFS(Raw_Data_Combined[Net Amount EUR],Raw_Data_Combined[GEO], Dashboards!B45) -> 149085.7 | E45: =VLOOKUP(B45,Tasks!$C$27:$E$36,3,FALSE) -> 0.56481481 | G45: =Tasks!C62 -> Stripe | H45: =Tasks!D62 -> 0.53571429 | I45: =Tasks!E62 -> 0.47368421 | J45: =Tasks!F62 -> 0.57692308
B46: FR | C46: 101 | D46: =SUMIFS(Raw_Data_Combined[Net Amount EUR],Raw_Data_Combined[GEO], Dashboards!B46) -> 174641.67 | E46: =VLOOKUP(B46,Tasks!$C$27:$E$36,3,FALSE) -> 0.63366337 | G46: =Tasks!C63 -> Checkout.com | H46: =Tasks!D63 -> 0.54545455 | I46: =Tasks!E63 -> 0.65384615 | J46: =Tasks!F63 -> 0.57142857
B47: SE | C47: 100 | D47: =SUMIFS(Raw_Data_Combined[Net Amount EUR],Raw_Data_Combined[GEO], Dashboards!B47) -> 9240.6298 | E47: =VLOOKUP(B47,Tasks!$C$27:$E$36,3,FALSE) -> 0.49 | G47: =Tasks!C64 -> PaySafe | H47: =Tasks!D64 -> 0.62962963 | I47: =Tasks!E64 -> 0.43478261 | J47: =Tasks!F64 -> 0.7
B48: NO | C48: 98 | D48: =SUMIFS(Raw_Data_Combined[Net Amount EUR],Raw_Data_Combined[GEO], Dashboards!B48) -> 11128.355 | E48: =VLOOKUP(B48,Tasks!$C$27:$E$36,3,FALSE) -> 0.58163265 | G48: =Tasks!C65 -> Adyen | H48: =Tasks!D65 -> 0.63157895 | I48: =Tasks!E65 -> 0.47368421 | J48: =Tasks!F65 -> 0.5
B49: PL | C49: 97 | D49: =SUMIFS(Raw_Data_Combined[Net Amount EUR],Raw_Data_Combined[GEO], Dashboards!B49) -> 35308.793 | E49: =VLOOKUP(B49,Tasks!$C$27:$E$36,3,FALSE) -> 0.57731959
B50: IT | C50: 91 | D50: =SUMIFS(Raw_Data_Combined[Net Amount EUR],Raw_Data_Combined[GEO], Dashboards!B50) -> 120668.87 | E50: =VLOOKUP(B50,Tasks!$C$27:$E$36,3,FALSE) -> 0.6043956 | G50: Best PSP Provider per GEO
B51: DE | C51: 87 | D51: =SUMIFS(Raw_Data_Combined[Net Amount EUR],Raw_Data_Combined[GEO], Dashboards!B51) -> 95078 | E51: =VLOOKUP(B51,Tasks!$C$27:$E$36,3,FALSE) -> 0.49425287 | G51: TOP GEO | H51: Best PSP Provider
B52: ES | C52: 80 | D52: =SUMIFS(Raw_Data_Combined[Net Amount EUR],Raw_Data_Combined[GEO], Dashboards!B52) -> 110471.49 | E52: =VLOOKUP(B52,Tasks!$C$27:$E$36,3,FALSE) -> 0.5125 | G52: =Tasks!C69 -> NL | H52: =Tasks!D69 -> Adyen
G53: =Tasks!C70 -> GB | H53: =Tasks!D70 -> Checkout.com
G54: =Tasks!C71 -> CY | H54: =Tasks!D71 -> PaySafe

Sheet Pivot Tables
A1: REVENUE TREND | J1: TRANSACTION STATUS | P1: GEOGRAPHY | U1: FEES VS REVENUE | Z1: DECLINE ANALYSIS | AD1: PAYMENT METHODS
A3: Sum of Net Amount EUR | B3: Column Labels | J3: Row Labels | K3: Count of Transaction ID | L3: Count of Transaction ID2 | P3: Row Labels | Q3: Sum of Net Amount EUR | R3: Sum of Fee Amount EUR | U3: Row Labels | V3: Sum of Net Amount EUR | W3: Sum of Fee Amount EUR | Z3: Row Labels | AA3: Count of Transaction ID | AD3: Sum of Net Amount EUR | AE3: Column Labels
A4: Row Labels | B4: Adyen | C4: Checkout.com | D4: PaySafe | E4: Stripe | F4: Worldpay | G4: Grand Total | J4: Failed | K4: 0.218 | L4: 218 | P4: CY | Q4: 149085.7 | R4: 3941.84 | U4: Checkout.com | V4: 248501.67 | W4: 4812.9445 | Z4: Card Declined | AA4: 0.22477064 | AD4: Row Labels | AE4: Bank Transfer | AF4: Credit Card | AG4: Crypto | AH4: Debit Card | AI4: E-Wallet | AJ4: Grand Total
A5: January | B5: 15574.31 | C5: 18869.098 | D5: 9562.84 | E5: 7774.4612 | F5: 13840.215 | G5: 65620.924 | J5: Pending | K5: 0.228 | L5: 228 | P5: DE | Q5: 95078 | R5: 2415.9 | U5: PaySafe | V5: 215259.44 | W5: 7116.0222 | Z5: Expired Card | AA5: 0.18807339 | AD5: CY | AE5: 36554.85 | AF5: 19348.26 | AG5: 27807.32 | AH5: 29775.81 | AI5: 35599.46 | AJ5: 149085.7
A6: February | B6: 10240.509 | C6: 18733.817 | D6: 18757.012 | E6: 16302.442 | F6: 37973.004 | G6: 102006.78 | J6: Success | K6: 0.554 | L6: 554 | P6: ES | Q6: 110471.49 | R6: 2994.61 | U6: Adyen | V6: 192481.55 | W6: 4128.847 | Z6: Fraud Suspected | AA6: 0.23394495 | AD6: DE | AE6: 20269.65 | AF6: 8445.67 | AG6: 15982.45 | AH6: 30483.4 | AI6: 19896.83 | AJ6: 95078
A7: March | B7: 17571.851 | C7: 20022.457 | D7: 5377.133 | E7: 20915.745 | F7: 6685.7464 | G7: 70572.932 | J7: Grand Total | K7: 1 | L7: 1000 | P7: FR | Q7: 174641.67 | R7: 4468.82 | U7: Stripe | V7: 192114.78 | W7: 5737.6873 | Z7: Insufficient Funds | AA7: 0.15137615 | AD7: ES | AE7: 26764.37 | AF7: 22899.94 | AG7: 13313.15 | AH7: 24396.28 | AI7: 23097.75 | AJ7: 110471.49
A8: Grand Total | B8: 43386.669 | C8: 57625.372 | D8: 33696.985 | E8: 44992.648 | F8: 58498.966 | G8: 238200.64 | P8: GB | Q8: 157459.88 | R8: 3959.7298 | U8: Worldpay | V8: 172678.72 | W8: 4427.6302 | Z8: Technical Error | AA8: 0.20183486 | AD8: FR | AE8: 27974.7 | AF8: 28161.95 | AG8: 51710.05 | AH8: 30725.79 | AI8: 36069.18 | AJ8: 174641.67
P9: IT | Q9: 120668.87 | R9: 2991.8 | U9: Grand Total | V9: 1021036.2 | W9: 26223.131 | Z9: Grand Total | AA9: 1 | AD9: GB | AE9: 33407.508 | AF9: 7441.6479 | AG9: 36354.084 | AH9: 51073.785 | AI9: 29182.854 | AJ9: 157459.88
J10: Status | K10: Count | L10: % of Total | M10: Bar | P10: NL | Q10: 157032.23 | R10: 3948.28 | AD10: IT | AE10: 28038.18 | AF10: 27945.02 | AG10: 21073.01 | AH10: 15123.32 | AI10: 28489.34 | AJ10: 120668.87
J11: ✓ Success | K11: =GETPIVOTDATA("Count of Transaction ID2",$J$3,"Status","Success") -> 554 | L11: =GETPIVOTDATA("Count of Transaction ID",$J$3,"Status","Success") -> 0.554 | M11: =REPT("█",ROUND(L11*30,0)) -> █████████████████ | P11: NO | Q11: 11471.264 | R11: 283.29171 | AD11: NL | AE11: 27450.79 | AF11: 39927.57 | AG11: 27302.25 | AH11: 36465.89 | AI11: 25885.73 | AJ11: 157032.23
J12: ⏳ Pending | K12: =GETPIVOTDATA("Count of Transaction ID2",$J$3,"Status","Pending") -> 228 | L12: =GETPIVOTDATA("Count of Transaction ID",$J$3,"Status","Pending") -> 0.228 | M12: =REPT("█",ROUND(L12*30,0)) -> ███████ | P12: PL | Q12: 35323.966 | R12: 962.18568 | AD12: NO | AE12: 1363.0141 | AF12: 2808.0473 | AG12: 3363.8074 | AH12: 2379.827 | AI12: 1556.5681 | AJ12: 11471.264
J13: ✗ Failed | K13: =GETPIVOTDATA("Count of Transaction ID2",$J$3,"Status","Failed") -> 218 | L13: =GETPIVOTDATA("Count of Transaction ID",$J$3,"Status","Failed") -> 0.218 | M13: =REPT("█",ROUND(L13*30,0)) -> ███████ | P13: SE | Q13: 9803.1029 | R13: 256.67399 | AD13: PL | AE13: 10994.241 | AF13: 4486.2096 | AG13: 7364.7304 | AH13: 7787.6931 | AI13: 4691.0923 | AJ13: 35323.966
P14: Grand Total | Q14: 1021036.2 | R14: 26223.131 | AD14: SE | AE14: 2609.8631 | AF14: 1432.0242 | AG14: 1464.3056 | AH14: 1586.8416 | AI14: 2710.0684 | AJ14: 9803.1029
AD15: Grand Total | AE15: 215427.17 | AF15: 162896.34 | AG15: 205735.16 | AH15: 229798.64 | AI15: 207178.87 | AJ15: 1021036.2
Q17: Country | R17: Net Revenue (€)
P18: FR | Q18: France | R18: =VLOOKUP(P18,$P$4:$Q$13,2,FALSE) -> 174641.67
P19: NL | Q19: Netherlands | R19: =VLOOKUP(P19,$P$4:$Q$13,2,FALSE) -> 157032.23
P20: PL | Q20: Poland | R20: =VLOOKUP(P20,$P$4:$Q$13,2,FALSE) -> 35323.966
P21: CY | Q21: Cyprus | R21: =VLOOKUP(P21,$P$4:$Q$13,2,FALSE) -> 149085.7
P22: GB | Q22: United Kingdom | R22: =VLOOKUP(P22,$P$4:$Q$13,2,FALSE) -> 157459.88
P23: NO | Q23: Norway | R23: =VLOOKUP(P23,$P$4:$Q$13,2,FALSE) -> 11471.264
P24: IT | Q24: Italy | R24: =VLOOKUP(P24,$P$4:$Q$13,2,FALSE) -> 120668.87
P25: ES | Q25: Spain | R25: =VLOOKUP(P25,$P$4:$Q$13,2,FALSE) -> 110471.49
P26: SE | Q26: Sweden | R26: =VLOOKUP(P26,$P$4:$Q$13,2,FALSE) -> 9803.1029
P27: DE | Q27: Germany | R27: =VLOOKUP(P27,$P$4:$Q$13,2,FALSE) -> 95078

Sheet Dynamic Dashboard
